{"type":"Topology","objects":{"E06000043":{"type":"GeometryCollection","geometries":[{"type":"Polygon","arcs":[[0,1,2,3]],"properties":{"objectid":973,"cmwd11cd":"E36000973","cmwd11nm":"Brunswick and Adelaide","cmwd11nmw":null,"lad11cd":"E06000043","lad11nm":"Brighton and Hove","lad11nmw":null,"st_areasha":527265.148951485,"st_lengths":3156.133679375429}},{"type":"Polygon","arcs":[[-3,4,5,6]],"properties":{"objectid":974,"cmwd11cd":"E36000974","cmwd11nm":"Central Hove","cmwd11nmw":null,"lad11cd":"E06000043","lad11nm":"Brighton and Hove","lad11nmw":null,"st_areasha":762602.726576795,"st_lengths":3829.73835611177}},{"type":"Polygon","arcs":[[7,8,9,10,11,12]],"properties":{"objectid":975,"cmwd11cd":"E36000975","cmwd11nm":"East Brighton","cmwd11nmw":null,"lad11cd":"E06000043","lad11nm":"Brighton and Hove","lad11nmw":null,"st_areasha":4067842.941112105,"st_lengths":9438.872770436874}},{"type":"Polygon","arcs":[[13,14,15,-4,-7,16,17]],"properties":{"objectid":976,"cmwd11cd":"E36000976","cmwd11nm":"Goldsmid","cmwd11nmw":null,"lad11cd":"E06000043","lad11nm":"Brighton and Hove","lad11nmw":null,"st_areasha":1411096.88346795,"st_lengths":5941.353639079528}},{"type":"Polygon","arcs":[[18,19,20,21,22,23]],"properties":{"objectid":977,"cmwd11cd":"E36000977","cmwd11nm":"Hangleton and Knoll","cmwd11nmw":null,"lad11cd":"E06000043","lad11nm":"Brighton and Hove","lad11nmw":null,"st_areasha":7259631.32589706,"st_lengths":12906.366297328203}},{"type":"Polygon","arcs":[[-12,24,25,26]],"properties":{"objectid":978,"cmwd11cd":"E36000978","cmwd11nm":"Hanover and Elm Grove","cmwd11nmw":null,"lad11cd":"E06000043","lad11nm":"Brighton and Hove","lad11nmw":null,"st_areasha":1409948.948837335,"st_lengths":5679.956057597985}},{"type":"Polygon","arcs":[[27,28,29,30,31,32]],"properties":{"objectid":979,"cmwd11cd":"E36000979","cmwd11nm":"Hollingdean and Stanmer","cmwd11nmw":null,"lad11cd":"E06000043","lad11nm":"Brighton and Hove","lad11nmw":null,"st_areasha":7414396.58069069,"st_lengths":14199.239132630733}},{"type":"Polygon","arcs":[[33,-18,34,35,-20,36]],"properties":{"objectid":980,"cmwd11cd":"E36000980","cmwd11nm":"Hove Park","cmwd11nmw":null,"lad11cd":"E06000043","lad11nm":"Brighton and Hove","lad11nmw":null,"st_areasha":3553009.96455994,"st_lengths":9574.2948569405}},{"type":"Polygon","arcs":[[37,-13,-27,-28,38]],"properties":{"objectid":981,"cmwd11cd":"E36000981","cmwd11nm":"Moulsecoomb and Bevendean","cmwd11nmw":null,"lad11cd":"E06000043","lad11nm":"Brighton and Hove","lad11nmw":null,"st_areasha":5830222.85488944,"st_lengths":11275.77171869336}},{"type":"Polygon","arcs":[[-23,39,40]],"properties":{"objectid":982,"cmwd11cd":"E36000982","cmwd11nm":"North Portslade","cmwd11nmw":null,"lad11cd":"E06000043","lad11nm":"Brighton and Hove","lad11nmw":null,"st_areasha":6113428.216435455,"st_lengths":10654.272868117145}},{"type":"Polygon","arcs":[[-32,41,42]],"properties":{"objectid":983,"cmwd11cd":"E36000983","cmwd11nm":"Patcham","cmwd11nmw":null,"lad11cd":"E06000043","lad11nm":"Brighton and Hove","lad11nmw":null,"st_areasha":8094003.970738585,"st_lengths":13361.605973599739}},{"type":"Polygon","arcs":[[43,-14,-34,44,-30]],"properties":{"objectid":984,"cmwd11cd":"E36000984","cmwd11nm":"Preston Park","cmwd11nmw":null,"lad11cd":"E06000043","lad11nm":"Brighton and Hove","lad11nmw":null,"st_areasha":1675236.907429105,"st_lengths":6054.056282527594}},{"type":"Polygon","arcs":[[-11,45,46,47,-25]],"properties":{"objectid":985,"cmwd11cd":"E36000985","cmwd11nm":"Queen's Park","cmwd11nmw":null,"lad11cd":"E06000043","lad11nm":"Brighton and Hove","lad11nmw":null,"st_areasha":1204748.251375485,"st_lengths":5167.490373382253}},{"type":"Polygon","arcs":[[-47,48,-1,-16,49]],"properties":{"objectid":986,"cmwd11cd":"E36000986","cmwd11nm":"Regency","cmwd11nmw":null,"lad11cd":"E06000043","lad11nm":"Brighton and Hove","lad11nmw":null,"st_areasha":882983.28006231,"st_lengths":4777.872669134476}},{"type":"Polygon","arcs":[[-9,50,51]],"properties":{"objectid":987,"cmwd11cd":"E36000987","cmwd11nm":"Rottingdean Coastal","cmwd11nmw":null,"lad11cd":"E06000043","lad11nm":"Brighton and Hove","lad11nmw":null,"st_areasha":10200758.097297754,"st_lengths":23447.60582655895}},{"type":"Polygon","arcs":[[52,53,-40,-22]],"properties":{"objectid":988,"cmwd11cd":"E36000988","cmwd11nm":"South Portslade","cmwd11nmw":null,"lad11cd":"E06000043","lad11nm":"Brighton and Hove","lad11nmw":null,"st_areasha":1877542.05177409,"st_lengths":6390.187510883312}},{"type":"Polygon","arcs":[[-26,-48,-50,-15,-44,-29]],"properties":{"objectid":989,"cmwd11cd":"E36000989","cmwd11nm":"St. Peter's and North Laine","cmwd11nmw":null,"lad11cd":"E06000043","lad11nm":"Brighton and Hove","lad11nmw":null,"st_areasha":1431758.21314064,"st_lengths":5980.329376005852}},{"type":"Polygon","arcs":[[-17,-6,54,55,-35]],"properties":{"objectid":990,"cmwd11cd":"E36000990","cmwd11nm":"Westbourne","cmwd11nmw":null,"lad11cd":"E06000043","lad11nm":"Brighton and Hove","lad11nmw":null,"st_areasha":956787.517153855,"st_lengths":4155.963136370235}},{"type":"Polygon","arcs":[[-56,56,-53,-21,-36]],"properties":{"objectid":991,"cmwd11cd":"E36000991","cmwd11nm":"Wish","cmwd11nmw":null,"lad11cd":"E06000043","lad11nm":"Brighton and Hove","lad11nmw":null,"st_areasha":1477911.18255044,"st_lengths":5348.612848245433}},{"type":"Polygon","arcs":[[-42,-31,-45,-37,-19,57]],"properties":{"objectid":992,"cmwd11cd":"E36000992","cmwd11nm":"Withdean","cmwd11nmw":null,"lad11cd":"E06000043","lad11nm":"Brighton and Hove","lad11nmw":null,"st_areasha":8116026.7412378,"st_lengths":17221.8503379088}},{"type":"Polygon","arcs":[[-51,-8,-38,58]],"properties":{"objectid":993,"cmwd11cd":"E36000993","cmwd11nm":"Woodingdean","cmwd11nmw":null,"lad11cd":"E06000043","lad11nm":"Brighton and Hove","lad11nmw":null,"st_areasha":8427159.82833278,"st_lengths":15586.83513607152}}]}},"arcs":[[[-0.15290271256525,50.82620263814566],[-0.152314976912573,50.82605480613203],[-0.15535140471159,50.82133032230387]],[[-0.15535140471159,50.82133032230387],[-0.16274795588527,50.82245170649493],[-0.16302722317609,50.822247412303895],[-0.165326189916813,50.82250033894127]],[[-0.165326189916813,50.82250033894127],[-0.164704077329362,50.82413296611127],[-0.165905221614229,50.8241743618871],[-0.164399634619417,50.82932352633385]],[[-0.164399634619417,50.82932352633385],[-0.160851369546462,50.828724365569144],[-0.161121812125117,50.82791371490437],[-0.15290271256525,50.82620263814566]],[[-0.165326189916813,50.82250033894127],[-0.170623848205524,50.82319874774672],[-0.173152462102297,50.82317359076241],[-0.179729468420859,50.823771076237584]],[[-0.179729468420859,50.823771076237584],[-0.177092285724407,50.828221837751855],[-0.175890933698698,50.832116616498844]],[[-0.175890933698698,50.832116616498844],[-0.171089104853579,50.83145864545988],[-0.171364775570757,50.830836906397714],[-0.170791987546106,50.83073980426825],[-0.170958250332695,50.83037365694529],[-0.164399634619417,50.82932352633385]],[[-0.092618278694028,50.8344737711883],[-0.090727215673947,50.83386000547181],[-0.088430663477171,50.83194522198314],[-0.085616431769054,50.827897380041286],[-0.082229263973681,50.81989687212052],[-0.081048256265993,50.81850307400042]],[[-0.081048256265993,50.81850307400042],[-0.084930044069472,50.819826086227046],[-0.089227319926444,50.81984617761456],[-0.091427547574457,50.81913115182376],[-0.095120732389594,50.81675937648899],[-0.098484088398655,50.81568180373658],[-0.102409750138638,50.81631416775488],[-0.102098566438793,50.81688028587839],[-0.104699388629204,50.81744873645957],[-0.105123737237861,50.81682242839142],[-0.109629210146989,50.817832710733654],[-0.110422240714191,50.816056529373675],[-0.111493502857615,50.81575730797185],[-0.111531356337417,50.81383481818688]],[[-0.111531356337417,50.81383481818688],[-0.118347428456624,50.81546144767046],[-0.118618483963389,50.81500527420216],[-0.119315748156848,50.81542489038205],[-0.122188568051242,50.81611788323688]],[[-0.122188568051242,50.81611788323688],[-0.121291733801761,50.81822795513308],[-0.118977436804723,50.82066237428724],[-0.118171708199726,50.820501002805095],[-0.11618489570098,50.823224880321696],[-0.118101646250176,50.823937586924636],[-0.117626030376183,50.824358975384676],[-0.118631767124536,50.82505697180307],[-0.117125824201246,50.82592044070413],[-0.117402869153502,50.82605800197838],[-0.116967152868645,50.82640450508452],[-0.116712699834066,50.82626997789481],[-0.116281672553027,50.82657061196619]],[[-0.116281672553027,50.82657061196619],[-0.115343120577492,50.82702496770353],[-0.11327559526769,50.82730187057332],[-0.110911961804636,50.83135974710526],[-0.107821264541707,50.83255813751704],[-0.104585439723484,50.834495231378405],[-0.102009065586963,50.83487606914001]],[[-0.102009065586963,50.83487606914001],[-0.097025370837429,50.8341679565724],[-0.092618278694028,50.8344737711883]],[[-0.148793509316235,50.83311649643004],[-0.14696220540613,50.831588003009784]],[[-0.14696220540613,50.831588003009784],[-0.145919561814726,50.8302294613505]],[[-0.145919561814726,50.8302294613505],[-0.148373887271769,50.83015328406745],[-0.149587038151184,50.82924876502907],[-0.149826775066919,50.82936322208444],[-0.151341451317513,50.828158537301064],[-0.150737657143603,50.82791240634594],[-0.151173201783969,50.82749206581752],[-0.151938978155101,50.8277371683772],[-0.15290271256525,50.82620263814566]],[[-0.175890933698698,50.832116616498844],[-0.175456877175932,50.8338871905905],[-0.175679497275092,50.83550073848362]],[[-0.175679497275092,50.83550073848362],[-0.171463202017832,50.83500571058992],[-0.171138174305672,50.83601791011419],[-0.171838170571137,50.83609814064085],[-0.171866789261795,50.83692879595081],[-0.17053050170416,50.83837400064909],[-0.169999351205361,50.83837107152711],[-0.156473981781961,50.83432194431327],[-0.148793509316235,50.83311649643004]],[[-0.186160366143382,50.86798721264499],[-0.184260590389969,50.86628922518066],[-0.182842005853687,50.8664011376856],[-0.181774016791217,50.8623244381343],[-0.173466418941364,50.857432249194595]],[[-0.173466418941364,50.857432249194595],[-0.173716678844434,50.85630199787726],[-0.17620725100105,50.85289445468261],[-0.17848584200794,50.85123283202959],[-0.181214132681527,50.85027794726952],[-0.182391424094325,50.847552064036115],[-0.183304155888089,50.847097671688864],[-0.18152266741578,50.84621725149953],[-0.182236099975431,50.84507797585006],[-0.183052215676615,50.84531644806719],[-0.184755513438158,50.842793878063034],[-0.185559048177532,50.84288104071131],[-0.185830253654617,50.84248139814436],[-0.185980659424751,50.8420097137574],[-0.1852605450665,50.841921124015],[-0.185951924628134,50.83970934224628],[-0.186579159140861,50.83979912349509],[-0.186558707417589,50.839410249047326],[-0.185875393899601,50.839301599714425],[-0.185811056540246,50.8381402902627],[-0.18708303851758,50.837975649255874],[-0.186897980176678,50.835932766212444]],[[-0.186897980176678,50.835932766212444],[-0.193875638451632,50.83580435052106],[-0.20426684594451,50.83511106366906]],[[-0.20426684594451,50.83511106366906],[-0.202704186438219,50.837483175685605],[-0.205412058560481,50.83761835866612],[-0.204604958638718,50.842290300242475],[-0.205159254782438,50.84413461577511],[-0.2067590072476,50.846466299962884]],[[-0.2067590072476,50.846466299962884],[-0.208145570661875,50.8486939270495],[-0.210082993423278,50.85357074998412],[-0.21012214836449,50.855033815592684],[-0.209085708924326,50.856644124907106],[-0.210368197980669,50.86041265431293],[-0.212311094824999,50.86988203256457]],[[-0.212311094824999,50.86988203256457],[-0.207685581854111,50.86992258426031],[-0.203829627953688,50.86950444800883],[-0.201064599642338,50.875274962204806],[-0.19934806228834,50.87433193387895],[-0.197414851319193,50.86953774462872],[-0.195780852832401,50.86896833012594],[-0.192797919632759,50.86906160146695],[-0.187645082802974,50.86844471150054],[-0.186160366143382,50.86798721264499]],[[-0.116281672553027,50.82657061196619],[-0.116753050802697,50.82713770132159],[-0.121081676734395,50.82837496846777],[-0.125613702850288,50.82531955667063],[-0.128169927296359,50.82620606013619],[-0.130326584749784,50.82742706241191],[-0.132839488841912,50.827979996997165]],[[-0.132839488841912,50.827979996997165],[-0.125550907188092,50.83358908745977],[-0.122614890327052,50.83723953013634]],[[-0.122614890327052,50.83723953013634],[-0.104307616917538,50.83549808065663],[-0.102009065586963,50.83487606914001]],[[-0.08165065436884,50.86258735163285],[-0.089195207313315,50.86149233436504],[-0.094681128187793,50.859606782501885],[-0.095657882871661,50.85813144248578],[-0.097262783579476,50.857245581263506],[-0.099104982444678,50.856885243913396],[-0.102781825346969,50.85673008282362],[-0.105789652073076,50.855726575667504],[-0.107941666297629,50.85290212950734],[-0.109717338877784,50.848696273665276],[-0.110995911978433,50.84760974219305],[-0.11432656592958,50.84590881476418],[-0.117928981797853,50.842778424086035],[-0.122614890327052,50.83723953013634]],[[-0.122614890327052,50.83723953013634],[-0.124455746813358,50.83717022368758],[-0.124520324233887,50.83694098225468],[-0.125643135646499,50.83731431305649],[-0.125589787183693,50.83754732713928],[-0.126813633619821,50.83745542981637],[-0.127516620476509,50.83777883996469],[-0.131981580967876,50.83655790788086]],[[-0.131981580967876,50.83655790788086],[-0.132057150188956,50.83879248675713],[-0.133808673519454,50.846126744887904],[-0.133695808514583,50.84827817479601]],[[-0.133695808514583,50.84827817479601],[-0.133269488327579,50.852479857031305]],[[-0.133269488327579,50.852479857031305],[-0.13144764568386,50.85444024685944],[-0.127708419186359,50.85683401493664],[-0.121275798484128,50.858132869691666],[-0.120224614088309,50.859005504062075],[-0.11957362181161,50.86045663590221],[-0.118886694658828,50.86467211086819],[-0.117999466350096,50.866939707027086],[-0.116706868370011,50.86882390554318],[-0.117521043447173,50.869113163723604],[-0.118199858563048,50.870575832146024],[-0.118508219329215,50.872978746376894]],[[-0.118508219329215,50.872978746376894],[-0.113730603261852,50.873644598068346],[-0.109778017709436,50.872571478217075],[-0.103331674475894,50.87175905839255],[-0.101911152586647,50.87219017152527],[-0.102878829215723,50.874020098269646],[-0.096378597955092,50.87595876188609],[-0.09689122055154,50.87691603390394],[-0.095934741953315,50.87736185807499],[-0.093215679522809,50.875953884208606],[-0.092774971412375,50.87619764944811],[-0.083341898363564,50.87253522527693],[-0.084516133236347,50.87048847398781],[-0.08305387719386,50.86839843856157],[-0.081278934738862,50.86686535179735],[-0.082548831941431,50.86633033808134],[-0.08165065436884,50.86258735163285]],[[-0.153795226624399,50.838138302106884],[-0.151469284387519,50.83624859307033],[-0.148793509316235,50.83311649643004]],[[-0.175679497275092,50.83550073848362],[-0.182553154137974,50.83585535460129]],[[-0.182553154137974,50.83585535460129],[-0.186897980176678,50.835932766212444]],[[-0.173466418941364,50.857432249194595],[-0.16899074084274,50.855023658638075],[-0.160485151646754,50.84812085407562],[-0.15904051831608,50.846345058107076],[-0.157204455668056,50.84138262078268],[-0.153795226624399,50.838138302106884]],[[-0.073675689280656,50.85011267151161],[-0.083896292948289,50.848750082617464],[-0.080564032914485,50.84453711353462],[-0.083911007237041,50.84350016339177],[-0.086056599974801,50.84349042823244],[-0.086200976177122,50.842774122814795],[-0.08722437211112,50.84230879157529],[-0.088279327143312,50.84089774254328],[-0.086967789637024,50.84035097655963],[-0.087517852469497,50.83968267618945],[-0.088760299772521,50.8392434325528],[-0.087981757810177,50.83733371365488],[-0.090381672917881,50.83675869698415],[-0.089392635104594,50.835760268269176],[-0.092618278694028,50.8344737711883]],[[-0.08165065436884,50.86258735163285],[-0.081218476796399,50.86248668642603],[-0.080084231777242,50.860101571355116],[-0.078428463324977,50.86034595311511],[-0.077246466417798,50.85321803233763],[-0.073675689280656,50.85011267151161]],[[-0.2067590072476,50.846466299962884],[-0.214080915015965,50.84484167134068],[-0.217118770089466,50.843375229099436],[-0.221603816078283,50.842399383531266],[-0.22439734402861,50.842345665397566]],[[-0.22439734402861,50.842345665397566],[-0.226075972174655,50.843820211934805],[-0.226834922385971,50.84504870280336],[-0.227755976643643,50.845149047486],[-0.229047607911827,50.84773294828011],[-0.232765309303692,50.85052541502559],[-0.233814444069916,50.85182749268091],[-0.234813678582259,50.85693794361244],[-0.237425771105405,50.85813857570796],[-0.238185096427069,50.86136916409663],[-0.23993672142706,50.86229322322062],[-0.243148962499478,50.862851606977905],[-0.24340351951524,50.86322598552006],[-0.239007753034122,50.86461956440072],[-0.238229746687807,50.865465006896805],[-0.237670066886803,50.867303090871346],[-0.237185892921707,50.8691369509902],[-0.235981934019746,50.87120815059368],[-0.23225112885946,50.87457586911264],[-0.231101366835642,50.875357183912186],[-0.225149263241946,50.87759904194039],[-0.223952228527761,50.87748642951366],[-0.223076746594075,50.87665731360235],[-0.222984817462821,50.87571057005614],[-0.212575670468892,50.87459733165327],[-0.212311094824999,50.86988203256457]],[[-0.133269488327579,50.852479857031305],[-0.137556175207786,50.85301876002272],[-0.139375082618318,50.85276625791578],[-0.150629814420034,50.85298923681532],[-0.153439903311696,50.85271444696312],[-0.1535442262883,50.853705461236196],[-0.152483706156072,50.855621537454674],[-0.154240535393163,50.855934443764895],[-0.15367739115453,50.858676865363506],[-0.154138252998511,50.86201209534984],[-0.15766219005025,50.86948908441465],[-0.163667830422958,50.87675769370693],[-0.164851378388618,50.880324666645784]],[[-0.164851378388618,50.880324666645784],[-0.160083370234588,50.88038273995526],[-0.157858923924155,50.879718033681584],[-0.153880272216569,50.87919464152806],[-0.151394594126741,50.879279424751296],[-0.151597556942559,50.88432051379986],[-0.150947648165679,50.88486247987891],[-0.143032130983513,50.88639815247201],[-0.140514604734897,50.88523643463139],[-0.140825650311676,50.8837078128335],[-0.135560359563001,50.88399713073738],[-0.13342935364728,50.88605251875123],[-0.133956811279087,50.88455884221613],[-0.134243181624413,50.880166033104835],[-0.133703369732649,50.87752200632715],[-0.127922250475035,50.87814088683892],[-0.125460131334372,50.87756803019936],[-0.12262816537076,50.877392129358796],[-0.122718526141235,50.8756027510309],[-0.120652653369193,50.875539860246676],[-0.120218030882384,50.872844387517816],[-0.118508219329215,50.872978746376894]],[[-0.131981580967876,50.83655790788086],[-0.131977582182756,50.83605323948469],[-0.13798428424212,50.83484506135889],[-0.13710376412935,50.833022193762595],[-0.140835701396341,50.83257442236312],[-0.144202756154121,50.83126173202075],[-0.145790689602807,50.831367035552816],[-0.145803705623102,50.83164785134736],[-0.14696220540613,50.831588003009784]],[[-0.153795226624399,50.838138302106884],[-0.15185227599892,50.83859957217283],[-0.150196016604313,50.83838441964239],[-0.14999406167616,50.83856922256125],[-0.151355700408196,50.83934006235198],[-0.151320941362795,50.83903280068613],[-0.151995473331904,50.83914601771105],[-0.151536724329624,50.83997166019165],[-0.151744261291058,50.84097513862223],[-0.149558676325236,50.841389324194324],[-0.149764107474814,50.84255199596728],[-0.145508245751953,50.84340543980751],[-0.142028945581084,50.84355242449451],[-0.135716419941948,50.848129702973935],[-0.133695808514583,50.84827817479601]],[[-0.122188568051242,50.81611788323688],[-0.128409868110366,50.8175454334798],[-0.132605694377902,50.81828813305217],[-0.13292949398253,50.81810801846734],[-0.134195777151923,50.8185780194217],[-0.135113818033174,50.81862957328509],[-0.13539420769414,50.818149251307545]],[[-0.13539420769414,50.818149251307545],[-0.134972342866755,50.820504497491626]],[[-0.134972342866755,50.820504497491626],[-0.134685829446691,50.82256234454407],[-0.133024355648398,50.82615790789334],[-0.132839488841912,50.827979996997165]],[[-0.13539420769414,50.818149251307545],[-0.137323822600921,50.81854163518536],[-0.137650133899721,50.817941513170055],[-0.137670173930338,50.81825845190351],[-0.138415752803841,50.81850420177956],[-0.144784674129345,50.81970296647236],[-0.14602915095403,50.81986576527918],[-0.146141555598396,50.81960939987367],[-0.148886628921582,50.82006582775258],[-0.152364654392061,50.820841428200744],[-0.152476218312381,50.820604827054794],[-0.15535140471159,50.82133032230387]],[[-0.145919561814726,50.8302294613505],[-0.14431460521895,50.825038279777225],[-0.143057220418504,50.82344422760971],[-0.139256159028144,50.82247164097974],[-0.136535179860306,50.820873955352674],[-0.134972342866755,50.820504497491626]],[[-0.081048256265993,50.81850307400042],[-0.078979718987179,50.81756419874488],[-0.076820552681346,50.81800172769114],[-0.074892205398777,50.8191446017426],[-0.072938318487481,50.81838827555403],[-0.071749314527229,50.81977990515308],[-0.070119731457703,50.82059392564251],[-0.070323651805478,50.820848264749785],[-0.069377115535549,50.82276100818083],[-0.068207625411208,50.82219661330208],[-0.068354516183035,50.82183746284201],[-0.06593588378954,50.821537434835385],[-0.062344878903729,50.82232241896978],[-0.058183547997807,50.82401525499025],[-0.048305179229543,50.82630594180353],[-0.047561360218405,50.82347279893579],[-0.046588035690841,50.82338545445614],[-0.045170680390044,50.826041194977186],[-0.045130927588928,50.8272296252853],[-0.044363837986456,50.82774475164938],[-0.043517219952619,50.82768019360247],[-0.042985552526227,50.82728629440882],[-0.042753664374498,50.82423952760543],[-0.0405786823693,50.824226410429816]],[[-0.0405786823693,50.824226410429816],[-0.040869232393125,50.82366281768424],[-0.043526368313864,50.822808854169004],[-0.044232086066026,50.82294571051121],[-0.043895859258919,50.821783345029345],[-0.044380319433631,50.82123382775466],[-0.040564707708135,50.820863051469225],[-0.038096490527455,50.82093850240059],[-0.03168082187416,50.81820849841894],[-0.029413353856846,50.81682370913309],[-0.024749289191478,50.81742572347339],[-0.018837396010627,50.82123904842384],[-0.01771148166922,50.819057596960576],[-0.014994929682968,50.81568250130826],[-0.014411212665898,50.81428288010986],[-0.019032950856752,50.81229632593485],[-0.02648984083941,50.80777437836957],[-0.030176881816167,50.80395281219993],[-0.032802369691583,50.801870771373466],[-0.035508327703291,50.800334195582714],[-0.036614847988487,50.798926264539226],[-0.036667315669302,50.79885968868557],[-0.036871108504652,50.79860317608587],[-0.036823872043556,50.79895048792085],[-0.037738012503007,50.79884712345531],[-0.037542010715739,50.79918832193512],[-0.038156511091552,50.79925802844791],[-0.038200356799662,50.79902398752818],[-0.038256871694764,50.79933526202438],[-0.038939764461359,50.799398911390504],[-0.039248428200818,50.79917832845559],[-0.039007046219228,50.79952057281654],[-0.039315044803971,50.79965526922342],[-0.041249331793229,50.799932430854],[-0.041391311982593,50.79966046666923],[-0.041686244185453,50.799938862338664],[-0.041844726682278,50.79967885428204],[-0.042184330330487,50.799906731993914],[-0.042361940661835,50.79956252780444],[-0.042741836553141,50.799845938916796],[-0.042968370651692,50.79958708897267],[-0.042844832319741,50.79982697974907],[-0.043531870174303,50.79992664797646],[-0.043651044261178,50.79969027580368],[-0.04374588108199,50.80000219006548],[-0.044599190180876,50.799926562857394],[-0.045436052322097,50.80014386397721],[-0.045364811010096,50.80035403450146],[-0.048542667054729,50.800936122832866],[-0.048682618128239,50.80067493099649],[-0.04896012114899,50.80096469474008],[-0.049123734399693,50.80064902036752],[-0.049447736614662,50.80091259254476],[-0.049596843888004,50.80060385902879],[-0.049958234407699,50.800889644881224],[-0.050222110714561,50.80061970801894],[-0.050071059554771,50.80083845907899],[-0.050830491162538,50.800973465829436],[-0.051168153547897,50.80070387536965],[-0.051083285628708,50.80093541198358],[-0.052782152924395,50.801245328775494],[-0.052965684845997,50.80082475938109],[-0.053376278687584,50.80102046493543],[-0.053605462890804,50.80083361139412],[-0.05477477221922,50.80148903089437],[-0.054976531212747,50.801245053380185],[-0.055372482006431,50.80165638548644],[-0.055700198707146,50.80145497695167],[-0.055564730638561,50.801674897821584],[-0.056093046422243,50.801872592546],[-0.059901801618075,50.80278419328768],[-0.060247363891624,50.80249490527583],[-0.06002656109905,50.8028222449067],[-0.061843637930202,50.80336516073491],[-0.062154392805444,50.80319672200559],[-0.062015367546495,50.80346874073171],[-0.063055900424567,50.80353549921538],[-0.062947781961076,50.8037126845869],[-0.063831226652492,50.803939634909824],[-0.063984349213315,50.803772147970484],[-0.06478784533923,50.804182178413924],[-0.065111605629321,50.803972572777575],[-0.064927680904713,50.80419888482428],[-0.066190914845475,50.804578710586775],[-0.066816401009712,50.80469343192847],[-0.066996973737057,50.80448054615659],[-0.066922762515891,50.8047302681522],[-0.068050480894015,50.804886553256026],[-0.071401722223149,50.806199461559245],[-0.071867747222303,50.80608573168586],[-0.073902110621502,50.80683982042443],[-0.075663866462617,50.80707844976769],[-0.075641650737675,50.80730836573875],[-0.077230384542695,50.80775100555168],[-0.07807782378354,50.807440258204245],[-0.077837263379646,50.80769894336752],[-0.078317930597211,50.80785167029201],[-0.078627030638281,50.80758331740245],[-0.078406588117337,50.8079043966529],[-0.080365049816305,50.80836929130307],[-0.080267327840516,50.80857005774691],[-0.08121487766452,50.808864483007724],[-0.090486545925173,50.81115460766294],[-0.090947963029028,50.81115316868994],[-0.092299978249571,50.809017457092345],[-0.093027497060443,50.80833855972645],[-0.093672867977772,50.80803789937117],[-0.094694035523514,50.80781620968908],[-0.095398339778915,50.80777644222071],[-0.097035766813912,50.80784801435008],[-0.101069339251152,50.80830512129821],[-0.104526684806782,50.80895497447456],[-0.103054795367196,50.80894905189259],[-0.101229011705477,50.80842824916688],[-0.097040112425336,50.80793272966982],[-0.094873806841001,50.807900824005564],[-0.094546103427785,50.80797851542648],[-0.092792659785098,50.808656408225595],[-0.092271459750441,50.80936188828276],[-0.092077801669518,50.80997302724126],[-0.092370824516486,50.810064692253],[-0.102046723945158,50.81157797753642],[-0.10281200452568,50.809894949372335],[-0.102593077567695,50.810708087270385],[-0.106163399371467,50.81102604957976],[-0.106306917023157,50.80958472019556],[-0.104807065979271,50.807675100263914],[-0.106509487255916,50.80980568918586],[-0.105893546086448,50.812221542878845],[-0.111531356337417,50.81383481818688]],[[-0.20426684594451,50.83511106366906],[-0.20668785155578,50.83031462913892],[-0.206858489520078,50.82619684593115]],[[-0.206858489520078,50.82619684593115],[-0.214468575223594,50.826984538019325],[-0.213725516469622,50.82978213488734],[-0.215015923208502,50.83009513650573],[-0.215096454107996,50.83237556988782],[-0.216001505310437,50.832330036912296],[-0.221337203155822,50.838502536030084],[-0.22439734402861,50.842345665397566]],[[-0.179729468420859,50.823771076237584],[-0.190166106227778,50.82503432368155]],[[-0.190166106227778,50.82503432368155],[-0.187719683515756,50.833200338303875],[-0.183662028477063,50.83271992747157],[-0.182553154137974,50.83585535460129]],[[-0.190166106227778,50.82503432368155],[-0.196846811723797,50.825679220437415],[-0.19765027655005,50.82561339781608],[-0.19767574778084,50.82528367079603],[-0.206858489520078,50.82619684593115]],[[-0.186160366143382,50.86798721264499],[-0.188173873089414,50.87383338177904],[-0.186151045563401,50.87500362729497],[-0.184696187106826,50.87509162203089],[-0.183497924609128,50.87600212361841],[-0.180286076267407,50.8803225495655],[-0.179727102617958,50.88306795264524],[-0.180847432909772,50.88774372679624],[-0.179206845754701,50.887771218505016],[-0.176237469606621,50.889891636762215],[-0.167759101582353,50.889351432635046],[-0.167035018008903,50.891787481533434],[-0.164287499573512,50.89175149148938],[-0.166595703087554,50.88500587699961],[-0.166599803466597,50.88446624596284],[-0.166053494224468,50.88422019978768],[-0.166889083293763,50.881331701647845],[-0.166549530311171,50.88016605503],[-0.164851378388618,50.880324666645784]],[[-0.073675689280656,50.85011267151161],[-0.070911806870418,50.84774374844285],[-0.069192662379013,50.845230995229706],[-0.070803173944514,50.84345420220448],[-0.071856113089265,50.84065629536643],[-0.061033899078414,50.84093839817245],[-0.058766828298185,50.84138010475249],[-0.056772847910653,50.84229043185078],[-0.052000594414338,50.843699428863005],[-0.047235896929429,50.84379700396642],[-0.043996611410363,50.84437955272183],[-0.041867135428786,50.84369710849273],[-0.041786773022158,50.84273245321531],[-0.041002048984174,50.84213463349806],[-0.035252642439704,50.84065005936337],[-0.034641904457749,50.838991094304895],[-0.037402619982915,50.837282692693385],[-0.036486564177529,50.83582362610396],[-0.037266794156068,50.83408641039821],[-0.037514602765284,50.82804258674838],[-0.0405786823693,50.824226410429816]]],"bbox":[-0.24340351951524,50.79860317608587,-0.014411212665898,50.891787481533434]}
