{"type":"Topology","objects":{"E06000035":{"type":"GeometryCollection","geometries":[{"type":"Polygon","arcs":[[0,1,2,3]],"properties":{"objectid":802,"cmwd11cd":"E36000802","cmwd11nm":"Chatham Central","cmwd11nmw":null,"lad11cd":"E06000035","lad11nm":"Medway","lad11nmw":null,"st_areasha":2132323.52381839,"st_lengths":7167.699370771723}},{"type":"Polygon","arcs":[[4,5]],"properties":{"objectid":803,"cmwd11cd":"E36000803","cmwd11nm":"Cuxton and Halling","cmwd11nmw":null,"lad11cd":"E06000035","lad11nm":"Medway","lad11nmw":null,"st_areasha":15133573.186294775,"st_lengths":20928.90129701984}},{"type":"Polygon","arcs":[[6,7,8,9,10]],"properties":{"objectid":804,"cmwd11cd":"E36000804","cmwd11nm":"Gillingham North","cmwd11nmw":null,"lad11cd":"E06000035","lad11nm":"Medway","lad11nmw":null,"st_areasha":2885759.41844333,"st_lengths":10533.223169803243}},{"type":"Polygon","arcs":[[11,12,13,14,-9]],"properties":{"objectid":805,"cmwd11cd":"E36000805","cmwd11nm":"Gillingham South","cmwd11nmw":null,"lad11cd":"E06000035","lad11nm":"Medway","lad11nmw":null,"st_areasha":1946806.59632786,"st_lengths":8145.897794604943}},{"type":"Polygon","arcs":[[15,16,17,18,19,20]],"properties":{"objectid":806,"cmwd11cd":"E36000806","cmwd11nm":"Hempstead and Wigmore","cmwd11nmw":null,"lad11cd":"E06000035","lad11nm":"Medway","lad11nmw":null,"st_areasha":4120020.95125253,"st_lengths":11889.512635555318}},{"type":"Polygon","arcs":[[-19,21,22,23,24]],"properties":{"objectid":807,"cmwd11cd":"E36000807","cmwd11nm":"Lordswood and Capstone","cmwd11nmw":null,"lad11cd":"E06000035","lad11nm":"Medway","lad11nmw":null,"st_areasha":5608409.60175817,"st_lengths":11548.712778508438}},{"type":"Polygon","arcs":[[-14,25,-20,-25,26,27,28,-1,29]],"properties":{"objectid":808,"cmwd11cd":"E36000808","cmwd11nm":"Luton and Wayfield","cmwd11nmw":null,"lad11cd":"E06000035","lad11nm":"Medway","lad11nmw":null,"st_areasha":2745689.41450958,"st_lengths":10040.724534061834}},{"type":"MultiPolygon","arcs":[[[30,31]],[[32]],[[33]]],"properties":{"objectid":809,"cmwd11cd":"E36000809","cmwd11nm":"Peninsula","cmwd11nmw":null,"lad11cd":"E06000035","lad11nm":"Medway","lad11nmw":null,"st_areasha":74844309.26900512,"st_lengths":70867.01605730732}},{"type":"Polygon","arcs":[[-24,34,-27]],"properties":{"objectid":810,"cmwd11cd":"E36000810","cmwd11nm":"Princes Park","cmwd11nmw":null,"lad11cd":"E06000035","lad11nm":"Medway","lad11nmw":null,"st_areasha":2001529.44017986,"st_lengths":8624.173155593304}},{"type":"Polygon","arcs":[[35,36,-16,37,38]],"properties":{"objectid":811,"cmwd11cd":"E36000811","cmwd11nm":"Rainham Central","cmwd11nmw":null,"lad11cd":"E06000035","lad11nm":"Medway","lad11nmw":null,"st_areasha":3329229.13352944,"st_lengths":8769.758225610345}},{"type":"Polygon","arcs":[[39,-36,40,-7,41]],"properties":{"objectid":812,"cmwd11cd":"E36000812","cmwd11nm":"Rainham North","cmwd11nmw":null,"lad11cd":"E06000035","lad11nm":"Medway","lad11nmw":null,"st_areasha":6102618.45991079,"st_lengths":20231.770176311205}},{"type":"Polygon","arcs":[[42,-17,-37,-40]],"properties":{"objectid":813,"cmwd11cd":"E36000813","cmwd11nm":"Rainham South","cmwd11nmw":null,"lad11cd":"E06000035","lad11nm":"Medway","lad11nmw":null,"st_areasha":5630866.03571135,"st_lengths":12194.128885196527}},{"type":"Polygon","arcs":[[-10,-15,-30,-4,43,44,45]],"properties":{"objectid":814,"cmwd11cd":"E36000814","cmwd11nm":"River","cmwd11nmw":null,"lad11cd":"E06000035","lad11nm":"Medway","lad11nmw":null,"st_areasha":4863018.31527784,"st_lengths":17117.146287491985}},{"type":"Polygon","arcs":[[-44,-3,46,47]],"properties":{"objectid":815,"cmwd11cd":"E36000815","cmwd11nm":"Rochester East","cmwd11nmw":null,"lad11cd":"E06000035","lad11nm":"Medway","lad11nmw":null,"st_areasha":1387411.21172161,"st_lengths":6083.636683372772}},{"type":"Polygon","arcs":[[-29,48,49,50,-47,-2]],"properties":{"objectid":816,"cmwd11cd":"E36000816","cmwd11nm":"Rochester South and Horsted","cmwd11nmw":null,"lad11cd":"E06000035","lad11nm":"Medway","lad11nmw":null,"st_areasha":3814296.097948075,"st_lengths":11233.555301612114}},{"type":"Polygon","arcs":[[-48,-51,51,-45]],"properties":{"objectid":817,"cmwd11cd":"E36000817","cmwd11nm":"Rochester West","cmwd11nmw":null,"lad11cd":"E06000035","lad11nm":"Medway","lad11nmw":null,"st_areasha":6024691.26929418,"st_lengths":14775.41882712996}},{"type":"Polygon","arcs":[[52,53,54,55]],"properties":{"objectid":818,"cmwd11cd":"E36000818","cmwd11nm":"Strood North","cmwd11nmw":null,"lad11cd":"E06000035","lad11nm":"Medway","lad11nmw":null,"st_areasha":2950558.397970235,"st_lengths":8014.170596842894}},{"type":"Polygon","arcs":[[-31,56,-56,57]],"properties":{"objectid":819,"cmwd11cd":"E36000819","cmwd11nm":"Strood Rural","cmwd11nmw":null,"lad11cd":"E06000035","lad11nm":"Medway","lad11nmw":null,"st_areasha":35210307.47878334,"st_lengths":41560.45830247299}},{"type":"Polygon","arcs":[[58,-6,59,-54]],"properties":{"objectid":820,"cmwd11cd":"E36000820","cmwd11nm":"Strood South","cmwd11nmw":null,"lad11cd":"E06000035","lad11nm":"Medway","lad11nmw":null,"st_areasha":3863328.132711385,"st_lengths":10005.40573680839}},{"type":"Polygon","arcs":[[-41,-39,60,-12,-8]],"properties":{"objectid":821,"cmwd11cd":"E36000821","cmwd11nm":"Twydall","cmwd11nmw":null,"lad11cd":"E06000035","lad11nm":"Medway","lad11nmw":null,"st_areasha":2966929.54532325,"st_lengths":7473.379619478197}},{"type":"Polygon","arcs":[[-28,-35,-23,61,-49]],"properties":{"objectid":822,"cmwd11cd":"E36000822","cmwd11nm":"Walderslade","cmwd11nmw":null,"lad11cd":"E06000035","lad11nm":"Medway","lad11nmw":null,"st_areasha":1929012.760159155,"st_lengths":7791.920072470868}},{"type":"Polygon","arcs":[[-61,-38,-21,-26,-13]],"properties":{"objectid":823,"cmwd11cd":"E36000823","cmwd11nm":"Watling","cmwd11nmw":null,"lad11cd":"E06000035","lad11nm":"Medway","lad11nmw":null,"st_areasha":2483267.00122363,"st_lengths":8632.437562263314}}]}},"arcs":[[[0.53577101918625,51.378217766786356],[0.536451051469377,51.37702478974783],[0.535963906478533,51.37549280293563],[0.536560395273913,51.374922234953615],[0.538834747606985,51.37402574772988],[0.538815777748959,51.37295582345194],[0.536368661859838,51.3712719839265],[0.529477566552299,51.36492796901244],[0.523127834633217,51.36241067085841]],[[0.523127834633217,51.36241067085841],[0.520364899543659,51.364240266885204],[0.522499196406213,51.37157328244784],[0.521435174534935,51.371640274482786],[0.521540625811047,51.3720688376319],[0.518548802608473,51.372411119575595],[0.51841858430352,51.37205417023035],[0.515906019304328,51.37241036733707],[0.516244145714512,51.37288967941237],[0.51584134415309,51.373065641539704],[0.51454055504785,51.372982012367345],[0.514687629491755,51.37451238974963],[0.514050413032673,51.37468619542895],[0.513145165351855,51.37437281751111],[0.512361054294713,51.37511816664996]],[[0.512361054294713,51.37511816664996],[0.512437587903931,51.37859019740324]],[[0.512437587903931,51.37859019740324],[0.513678315194995,51.378938636896066],[0.515574564695335,51.37821435414344],[0.516958602667133,51.379760441358684],[0.518279379411077,51.379994669698306],[0.518615497656494,51.38043535457544],[0.516771970983485,51.380839291334034],[0.518556286343174,51.381006891020476],[0.519105146918221,51.38163188375163],[0.521304573523271,51.381950621338625],[0.524558732061422,51.38082544321892],[0.528360333033404,51.37886724871709],[0.53577101918625,51.378217766786356]],[[0.476200544156359,51.377259685346765],[0.475632375436781,51.376239120224106],[0.474923413441253,51.37593839309042],[0.472026975228093,51.37558313456432],[0.471640807212553,51.37636481583685],[0.471285614298592,51.37638760164973],[0.471853927730827,51.375492343798946],[0.468317748268527,51.375025472309225],[0.464895810446972,51.373393053266405],[0.464510046039448,51.37348841071574],[0.464431481616493,51.372989071265074],[0.46099878958707,51.3706686773333],[0.451545465788469,51.36611238048029],[0.450226272093458,51.36452187742643],[0.449838289354262,51.363283325104184],[0.450241369989283,51.36103705480153],[0.449885865954144,51.35889929102558],[0.45121014061369,51.357305623420864],[0.45329343130525,51.35612688645261],[0.451180389831797,51.355456955246],[0.452284665378967,51.355664097845725],[0.453275792847566,51.355420279811135],[0.453800809695868,51.35580953027718],[0.455147312212952,51.355280314758915],[0.456480922174611,51.352900270027234],[0.455514097198775,51.35279191400849],[0.455524106494424,51.35257586614817],[0.456827230271097,51.35263395127358],[0.457588973283599,51.3513803179642],[0.457398933058742,51.350647634407444],[0.456488780476126,51.34990581685524],[0.451439895276554,51.348829705633804],[0.450248389949958,51.3480343451228],[0.449626444316158,51.3469032521299],[0.450200946085832,51.34628409951776],[0.452783322892908,51.34531526471684],[0.453609419063964,51.34459458846846],[0.453778277934636,51.343615144338905],[0.45327744509384,51.342385284958745],[0.453062854494737,51.34213253336177],[0.45250525473841,51.34217928939392],[0.452407317041374,51.34160927819953],[0.453458209454006,51.341790553264914],[0.455151410411164,51.34007126477868],[0.451308779867166,51.34040005132899],[0.44608638226782,51.34159848615506],[0.432954087779475,51.34446246118556],[0.428317233158094,51.346375574650494],[0.422547564973809,51.3467244130864],[0.420256472900461,51.34737443426328],[0.418301105940872,51.34698127078775],[0.412664183994828,51.34767319054434],[0.410376311589049,51.347238168588746],[0.408374844701946,51.34722451979624],[0.408752004424322,51.34611761340846],[0.40709048121413,51.34491680463363],[0.405623363674822,51.34435420256496],[0.401579299339076,51.3439191080788],[0.399005643117822,51.34523829683027],[0.402625594325808,51.349396017476415],[0.4029431800764,51.35241796689602],[0.405117465268569,51.35591894670395],[0.405828402232177,51.35575143552624],[0.406394238211371,51.35596738208087],[0.408855462522906,51.35928795436522],[0.414200726257339,51.36345659117728],[0.420095211953625,51.37210821148523],[0.419567910710064,51.37279098161429],[0.420857704853485,51.3740307242142],[0.421340137569154,51.37505695781401],[0.422600041594069,51.37556517217778],[0.425077271637928,51.37561105236222],[0.426629462313241,51.376046654802316],[0.431851344563065,51.38313221438986],[0.432810356893014,51.38584669194129],[0.43277447882293,51.38749974280682],[0.436307005410928,51.3883473643917],[0.44881083724599,51.388424876881565],[0.449029509547667,51.38947717369197],[0.449617565512085,51.38982827026401],[0.453669539545101,51.39091726358994],[0.454989783050924,51.39084549936834],[0.458377500878594,51.39375252930318]],[[0.458377500878594,51.39375252930318],[0.458394826764785,51.39345896375344],[0.462349666028174,51.39131075996632],[0.464339501794049,51.38984147638596],[0.468359123738247,51.38551587043197],[0.46963891073041,51.38472251548868],[0.469778875005562,51.384091760615675],[0.471546764078316,51.38256762858627],[0.476200544156359,51.377259685346765]],[[0.58406205069202,51.389763434536405],[0.583178743689772,51.38847777010533],[0.583644760700964,51.38832897089152],[0.583472004112846,51.38761047764631],[0.579285648703396,51.383189109722785],[0.578522486810162,51.381836955156075]],[[0.578522486810162,51.381836955156075],[0.569967873167888,51.38400551704694]],[[0.569967873167888,51.38400551704694],[0.559361938724629,51.38654924261649],[0.554934178872948,51.38662429620453],[0.551246146840872,51.3859913857666],[0.546586123549898,51.3868788640144],[0.544216469498797,51.38870589984952]],[[0.544216469498797,51.38870589984952],[0.539530323189433,51.38946686512561],[0.537525444389288,51.39087929917818],[0.539940218805283,51.39115530227731],[0.545022587491586,51.392995943265895],[0.542779931479643,51.395461502402675],[0.543373147590065,51.395735569173965],[0.543348615468479,51.39609676785063],[0.546176299547273,51.39624226190881],[0.550020488872762,51.39537879100613],[0.550677752742468,51.3961308139674],[0.553470065996055,51.394738793910925],[0.556886136373535,51.398575169218944]],[[0.556886136373535,51.398575169218944],[0.557218801768227,51.3983781196082],[0.555970820835682,51.39696261466141],[0.556416626149533,51.39706711821636],[0.556636150454576,51.39674931992586],[0.557990673649162,51.398089637142746],[0.558427891625629,51.39749903978641],[0.557740349551243,51.39728918262226],[0.55912082279009,51.396698677260076],[0.559317200588073,51.39594154025435],[0.560414813775708,51.39574576749153],[0.561079160211057,51.397444718506094],[0.562022471678275,51.39718845697581],[0.56150683593465,51.39691549297715],[0.560878172511549,51.395598018620255],[0.56131905887671,51.395537116639616],[0.561709408525683,51.39596122092463],[0.562709989789105,51.395727076996764],[0.563315417505146,51.39675722142545],[0.562649131669485,51.39427937070252],[0.5632440213954,51.39452990860275],[0.563380344698034,51.39552711641319],[0.565373250996898,51.39558065630497],[0.566886996517291,51.39454910264306],[0.569569667323259,51.394108058800775],[0.570529405406101,51.39299326284743],[0.570784900257279,51.393139671676096],[0.573837787077967,51.391638022040055],[0.573932567451397,51.3921234766591],[0.576429573047453,51.392142363552956],[0.576996703933409,51.39279370613645],[0.577710524349168,51.392754635653425],[0.577809529247438,51.39229100628624],[0.577237054991657,51.39172433824092],[0.578057465562051,51.391331222874086],[0.579065650956261,51.39003447975479],[0.581927832126964,51.39049046961275],[0.58406205069202,51.389763434536405]],[[0.569967873167888,51.38400551704694],[0.568358795262483,51.38248113684786],[0.569075463655487,51.379929880767634],[0.568038795366747,51.37709956506219]],[[0.568038795366747,51.37709956506219],[0.563042464367308,51.38056476269802],[0.558320258557782,51.38194789400453],[0.558048800127007,51.38318873675759],[0.557375077553981,51.38389244183958],[0.556766087105561,51.38390123584779],[0.553113882213014,51.37639316729083],[0.554137572935205,51.373689599471895],[0.555104701056891,51.372836547554094],[0.554067997232443,51.37300755027234]],[[0.554067997232443,51.37300755027234],[0.547211481666145,51.37419837073369],[0.537910255674494,51.37783776203479]],[[0.537910255674494,51.37783776203479],[0.537651494940584,51.37812311601701],[0.538045619345635,51.378427104101604],[0.537462762822232,51.378842264956624],[0.538101562408915,51.379216958152696],[0.537467856319194,51.379610232184966],[0.539978334728535,51.38401262439814],[0.542619387560242,51.383501996001876],[0.542452407974011,51.3856994635485],[0.544216469498797,51.38870589984952]],[[0.580603363345031,51.35852848636161],[0.580518666327034,51.35244989103657],[0.57979054075391,51.34966764620667],[0.581047827464392,51.34898601846718],[0.5819236365804,51.34915830514214],[0.582583827255659,51.34986332477878],[0.583501494666012,51.3498089010597],[0.583677085686812,51.350223266124665],[0.584234848177132,51.350179489688045],[0.584706957578215,51.34874334513749],[0.5873473996263,51.34864902758391],[0.590513120955207,51.347987134028145]],[[0.590513120955207,51.347987134028145],[0.590458196638328,51.34141484987763],[0.588234954983057,51.339043547575734],[0.585023461730244,51.336663381963554],[0.586159534676877,51.33567221577278],[0.586342198191995,51.33417320776391]],[[0.586342198191995,51.33417320776391],[0.58507708975551,51.33412113575608],[0.582816400761262,51.334672965665845],[0.581967094385455,51.335402266113256],[0.579456993097872,51.33588579161296],[0.577113963350467,51.337019496869566],[0.575576300834404,51.336256428704736],[0.575123505715179,51.33637613000265],[0.5736228396885,51.33506799373955],[0.571319174818603,51.336470555020355],[0.567337676453597,51.337248793086125],[0.565134983965239,51.33820196108607]],[[0.565134983965239,51.33820196108607],[0.565338623879239,51.340741256922286],[0.566396900117122,51.344618221407416],[0.569233134360212,51.34363764702743],[0.569565486196243,51.3471626214172],[0.568298734702004,51.34719042409613],[0.567762829832132,51.347546682012435],[0.566960627126793,51.347405079483096],[0.567106921306074,51.34860809197823],[0.565955496882714,51.348720563430724],[0.565923770265245,51.34905229227856],[0.568140249127515,51.34908101771393],[0.568107380266,51.349289551873945],[0.566151987768945,51.35328831258159],[0.566513763814957,51.353592473465284],[0.565954009985754,51.35437198186009],[0.565187124492482,51.35411897208456],[0.563914889950592,51.35590257023064],[0.565055071575653,51.35633094248407],[0.563768880586604,51.35827768397194],[0.563013638552275,51.35897957796472],[0.560534981928039,51.35992517657551],[0.558615735280719,51.36129468460573],[0.556601139558431,51.36219227552809],[0.556423991036631,51.36339689330078]],[[0.556423991036631,51.36339689330078],[0.556856096352998,51.36475642834998]],[[0.556856096352998,51.36475642834998],[0.560060307863739,51.366688575252255],[0.56336274951827,51.36479227148521],[0.566029680634655,51.3641267420932],[0.566264826083059,51.363654790117344],[0.568442680104107,51.36249351092995],[0.571847963355533,51.361495042571995],[0.572503293037228,51.36221639286208],[0.573879236861588,51.36238674185443],[0.580071416286518,51.36038769668069],[0.579463847128098,51.35885673035246],[0.580603363345031,51.35852848636161]],[[0.565134983965239,51.33820196108607],[0.558387543861395,51.33599300926841],[0.556128215968383,51.33322248307241],[0.556440135508913,51.331681135019046],[0.55564900734671,51.33108766622686],[0.550599586385277,51.33036849112318],[0.547595910646846,51.329021683260116],[0.547022591342622,51.328029404821166],[0.545678722884057,51.327354330005136],[0.541813793326307,51.32971310339068],[0.540356274706785,51.33121447597441],[0.540339046931571,51.33220071819154],[0.539007537253399,51.33333417022228]],[[0.539007537253399,51.33333417022228],[0.538426622926198,51.33454036940155],[0.538615236952981,51.336393724989456],[0.537825797842428,51.339076028210044],[0.538786187394041,51.341822933476365],[0.539037427604719,51.344081457325295]],[[0.539037427604719,51.344081457325295],[0.538929314307284,51.34555446114068],[0.540112406573469,51.347624552571546],[0.54062744211877,51.351792339461454],[0.541941824374208,51.35153356106678],[0.541814918274749,51.35113514790717],[0.542227201373898,51.35095437003859],[0.545081242227408,51.350667522317984],[0.545647786135603,51.35438167008939],[0.546700179616855,51.35758153764847],[0.549191535570883,51.36218919470805],[0.550214887486654,51.36571162161356],[0.550681370095211,51.36603876394755]],[[0.550681370095211,51.36603876394755],[0.55229215984751,51.36482539714296],[0.556423991036631,51.36339689330078]],[[0.554067997232443,51.37300755027234],[0.55302983843245,51.371576710380104],[0.554082518260257,51.36792361498203],[0.556339537362584,51.36600713800076],[0.556856096352998,51.36475642834998]],[[0.550681370095211,51.36603876394755],[0.549177959433969,51.3676095047491],[0.54589501521364,51.36381147268739],[0.545346941105057,51.363981685012256],[0.53901355877618,51.36042779456755],[0.538604167399275,51.36053291231165],[0.537990960580935,51.36004431436647],[0.536994551817995,51.36036809964205],[0.534511215434419,51.35772804233905],[0.530473095694093,51.3559588533156],[0.530298312694312,51.35560285140796],[0.530829006174015,51.35524871386814],[0.529379623470493,51.355485077482726],[0.528809748353698,51.35504853316464],[0.526239903844035,51.352518031051645],[0.526510338876258,51.35163793282659],[0.527456312459759,51.35175695228887],[0.526510164177161,51.350329210764656],[0.525133184013151,51.35012951652751]],[[0.525133184013151,51.35012951652751],[0.525022302772957,51.350489895182825]],[[0.525022302772957,51.350489895182825],[0.52481610528353,51.35185970845792],[0.522808039879513,51.35431797249577],[0.52329600613428,51.35621791918073],[0.522093742205108,51.35904382190428],[0.523267251217723,51.36094786660043],[0.523127834633217,51.36241067085841]],[[0.53577101918625,51.378217766786356],[0.537910255674494,51.37783776203479]],[[0.548752282166987,51.411540139465735],[0.54853905568226,51.414973622806905],[0.549171350309486,51.41979731317023],[0.548167877545514,51.41983443451625],[0.548349168032182,51.42286086501555],[0.546514350876711,51.426113748994986],[0.549043203496836,51.42713721859706],[0.548138377752685,51.42926168813931],[0.544703535335686,51.43195208920516],[0.54428951664609,51.431855821067366],[0.542693330823727,51.43462309902019],[0.541576409441786,51.43441168833211],[0.541636473084047,51.43419717480798],[0.533842241182698,51.43294487152404],[0.531940366851866,51.43462034142005],[0.530001057994366,51.43712952731633],[0.530308951810715,51.43720653010316],[0.529942241993692,51.4378620534953],[0.523267010094439,51.43600198128272],[0.518857992874098,51.4414217588615],[0.51783114829867,51.44135837184325],[0.517027364105638,51.44519213629156],[0.519007257466448,51.44517926924747],[0.519468214589302,51.447668976822904],[0.519370931862355,51.45102522731877],[0.520008179066695,51.452532550441916],[0.520056189570806,51.45421354329335],[0.52082345651647,51.456145310880046],[0.52180665770693,51.455673505885834],[0.522930042237924,51.45557647528541],[0.522146714958889,51.455991802970196],[0.521232804273076,51.45725093705558],[0.521455150938288,51.45911614875632],[0.525049098609,51.46240554848198],[0.525193838369361,51.46421845167924],[0.526424525177623,51.465981892520034],[0.526034276923691,51.46671169493891],[0.527819174967151,51.47029179359473],[0.528737583877875,51.47064886805273],[0.5284013348782,51.47107886818359],[0.526944763754823,51.47161578405632],[0.525928200482142,51.471228425600486],[0.526359728799915,51.47041137689949],[0.524551966638779,51.47032623092465],[0.524225563730847,51.470882817932],[0.524740217796939,51.47438598157108],[0.526206142458941,51.475501217673106],[0.528118345303084,51.47564800968549],[0.528837659536887,51.47625758332035],[0.530955431566657,51.47598073954934],[0.532204726297809,51.475055197826954],[0.533199206349938,51.4750921854374],[0.533586318682001,51.47568468357734],[0.533662522901797,51.476487159273894],[0.532985428969646,51.47697847520697],[0.532855301916622,51.4781650139327],[0.531922241535039,51.47817079674862],[0.53153887537417,51.4784786031842],[0.532314320592575,51.47864356545412],[0.532420895239904,51.47913684876421],[0.531058016885399,51.48017277344285],[0.531206401082902,51.480485290440335],[0.531750320979696,51.480526601128076],[0.531332874084125,51.48120844760155],[0.531829580965778,51.481255270986175],[0.532031029903764,51.48182299161609],[0.5313725259546,51.481897482966275],[0.531142347707457,51.48283880109172],[0.533090773232294,51.48391925740896],[0.532345756816968,51.48461623315859]],[[0.532345756816968,51.48461623315859],[0.538191426371537,51.48505203443335],[0.5455933357579,51.48634602044446],[0.548687616575383,51.48652255254534],[0.555318163028209,51.48441822715144],[0.555643816171725,51.48403336022716],[0.555346143514693,51.482831852863065],[0.554675468394005,51.48191547549293],[0.555622661998486,51.48089822954602],[0.555794523571784,51.48111213032799],[0.556244999854193,51.48084685705564],[0.556801556117685,51.48162897341183],[0.560144587771835,51.482262991754375],[0.560068733927603,51.48363455433242],[0.56163740201283,51.48417145336335],[0.567093330419703,51.483586139273605],[0.576231248787721,51.48374112330459],[0.57797160387881,51.48269638255235],[0.580958325290511,51.479948446066125],[0.581892083298754,51.47990271560569],[0.582724178316561,51.48047985126081],[0.583699920738273,51.480310865636625],[0.584001602904935,51.480194484491726],[0.583651873409373,51.47940971881579],[0.584175822070101,51.47912294468149],[0.583796139328832,51.47949021118852],[0.584325014022016,51.48041132755536],[0.58541417886052,51.48054112968336],[0.586177517504045,51.48030934575003],[0.586559238378556,51.48051319950722],[0.586640113839469,51.4833168969293],[0.587467806491253,51.483915686548436],[0.589698734294399,51.4834985681302],[0.59181662900313,51.48251184707488],[0.593486990895964,51.482575678655806],[0.601213713883766,51.4805912345249],[0.603280192164145,51.48088357709117],[0.611679078656136,51.47877555082991],[0.612189588588823,51.47888649818669],[0.613523722224201,51.47823613765064],[0.613209561580816,51.477402127876786],[0.614843298867898,51.47541832812281],[0.616927182076572,51.47455689766804],[0.618861870548486,51.47516583955473],[0.623122357450799,51.47559051468738],[0.626139787247667,51.47681641709891],[0.629761126974643,51.4773693780916],[0.630764480393404,51.477083333998614],[0.631529402155014,51.47745924764483],[0.639625407589778,51.477896127050215],[0.64399418276343,51.47854157764729],[0.647721247620764,51.47835223605648],[0.652376895781377,51.47614401606747],[0.653218147365829,51.4764182167737],[0.658544525447854,51.47666095525135],[0.661678548467569,51.47715023808333],[0.66250170995925,51.47681582288344],[0.663082028370821,51.47552717079445],[0.665028699864184,51.47474897087522],[0.667649129782826,51.47500240071193],[0.671389198505896,51.47447559006242],[0.671736936432397,51.47335231280903],[0.672895021682474,51.472958904388356],[0.672849883507095,51.47231049813259],[0.671733918202017,51.472635468343505],[0.672802107220342,51.47223244811924],[0.672232239452729,51.47201875914652],[0.672189648596778,51.47055082814657],[0.671860468149118,51.470438700264395],[0.67220748275442,51.470437110814984],[0.672064615352808,51.469742371436524],[0.673024212749738,51.46856734215245],[0.676356013892051,51.46636492719398],[0.681495894301949,51.46570419411896],[0.685201562665861,51.46485211938024],[0.6867560565914,51.463932302788706],[0.687688105304957,51.463080693331705],[0.68748597296562,51.46290004174579],[0.687823276113297,51.46297955393731],[0.689197674664072,51.46174180315469],[0.689405536407149,51.46111370043986],[0.688878006007529,51.459635340269486],[0.689444304677269,51.459471236838986],[0.690051513609545,51.46041884369702],[0.690808960994739,51.46049321964829],[0.69044510480659,51.46162684015282],[0.69167009941423,51.46059217967502],[0.690616613850156,51.46013603492672],[0.691310125988017,51.460004980851885],[0.691015206369159,51.45971582455028],[0.691506912336865,51.45989883085094],[0.691286259641766,51.460235818725735],[0.691798316189788,51.460519970089216],[0.692401481820271,51.46022369646377],[0.691704561489386,51.45968559362173],[0.691635224476171,51.4590701506774],[0.691163475356248,51.45898111689626],[0.691763095600545,51.45899164894506],[0.692008042569421,51.45931253109],[0.692298821744389,51.45877335610987],[0.692623778561676,51.458912510966236],[0.691975449485178,51.459664084103096],[0.692702218043963,51.46036699998679],[0.690727104229249,51.46179397462883],[0.690111398107267,51.461779311326126],[0.689297044891373,51.46235388668148],[0.688235256507287,51.46339826441723],[0.68877448677805,51.46389951356528],[0.68812863219827,51.463666958125025],[0.686193767266939,51.46504884729103],[0.683127573573482,51.466270430416195],[0.676597891399204,51.46734794700541],[0.673831321284836,51.46926763963592],[0.673422811739347,51.471221651042086],[0.672931983548229,51.47166998600052],[0.677629144363631,51.4726368081257],[0.680240279250421,51.4742070370859],[0.681817945179821,51.47394520440415],[0.687736918427625,51.474567908044705],[0.688732172670049,51.47383270437262],[0.694889804276704,51.472442813816194],[0.696135098322667,51.47187179476631],[0.700441002927817,51.471911199502],[0.701436359415333,51.47220577864292],[0.704874225292426,51.47074309557487],[0.71336309648026,51.46404718935461],[0.718022628611302,51.46152049787372],[0.719895618353889,51.45996409937031],[0.721049229975689,51.459895948927624],[0.722086741644395,51.459207133071224],[0.723432300824937,51.457261733702694],[0.724409075931007,51.453233577165015],[0.725096717237898,51.44679605106304],[0.724676629508334,51.446389335288245],[0.725183472497706,51.44614998856425],[0.724946305010953,51.44296496771405],[0.724276370249113,51.4429301566846],[0.723349733634183,51.44237959833119],[0.723162397835743,51.44104549247448],[0.718992277093524,51.43701630067162],[0.715128296208467,51.435152122457374],[0.711984174179421,51.43428403536356],[0.711329490099524,51.43499000037641],[0.710537059560279,51.43512165934805],[0.708860825131162,51.434640491295845],[0.707003365113274,51.43330896960062],[0.701577429844558,51.43268848027795],[0.699880289574125,51.433167423584734],[0.695863040430256,51.43308000251408],[0.692456535693215,51.432488175474454],[0.689380037404995,51.43293210517291],[0.679583391034283,51.43264376580664],[0.677196420002623,51.43301941952721],[0.67532250815993,51.43377818347811],[0.675013398788894,51.43425119683362],[0.67670460260543,51.43548628379276],[0.677703449904837,51.435684751585285],[0.67853979554194,51.43630340178497],[0.678349020415088,51.438256944295766],[0.677078387169053,51.439416639478004],[0.674279706833751,51.439526411272375],[0.673248429177945,51.44099181817349],[0.671342698937402,51.44227207683417],[0.670845566194974,51.44305157100222],[0.671324504159238,51.44314409525622],[0.670692742410795,51.44319537070179],[0.670709851926629,51.443711285342644],[0.671458034764183,51.44397669676523],[0.670600548807637,51.4441806175817],[0.671007108896231,51.44461120901816],[0.67235195851884,51.445013228435094],[0.673084803215259,51.44595265971927],[0.672647909282058,51.44645737213213],[0.673169502511359,51.44673691039904],[0.673366630393889,51.44639061906314],[0.673789893094886,51.447401876706074],[0.672066028294365,51.447979980348435],[0.671920657174063,51.447684660350525],[0.672618519542869,51.447334140481445],[0.671929764005314,51.446706704412],[0.671783549387054,51.44553349901101],[0.670469915654936,51.445099279528975],[0.669073666150069,51.44411195574416],[0.669529801951475,51.44415913678726],[0.668856116820819,51.44393611840283],[0.668916863579491,51.44334914742305],[0.66748054615941,51.4435248477223],[0.665208632499353,51.443094429144395],[0.664255656984702,51.44341382340239],[0.665384609688648,51.445522658171924],[0.663915173107604,51.44718324478439],[0.660281471809471,51.4486122908406],[0.65770372156909,51.448694155385134],[0.656566104265934,51.44829088260427],[0.655540571408639,51.447115092073794],[0.655570545149838,51.44663948518798],[0.65489791950995,51.44653328520898],[0.654611035341819,51.44600459716897],[0.653300526828398,51.446044159058644],[0.653040784185114,51.446281192125234],[0.65159454946824,51.44541891777617],[0.652210645847924,51.44522059877031],[0.652814857330541,51.44581047420645],[0.652625504204841,51.445548511899176],[0.65344059578852,51.445555247189105],[0.652252020568962,51.445140505503815],[0.651809301151287,51.44462880283421],[0.651203588653594,51.44465869510848],[0.651736309561876,51.44530687703652],[0.651341433137336,51.44492632031394],[0.651491467197072,51.445329510136055],[0.651041566697802,51.445240742988645],[0.651022408052833,51.44486067827892],[0.650360283176299,51.44503486749906],[0.65104557065541,51.44441580687531],[0.650474934050109,51.443882712054176],[0.65076959176684,51.44429882539152],[0.650568717612964,51.444632580006335],[0.650414328890122,51.44420340222172],[0.650194500920936,51.444632935423144],[0.649825034144991,51.44451626001901],[0.650034442966573,51.444851533450134],[0.650450045725763,51.44477018260313],[0.650035984861205,51.444977429340696],[0.64789885873297,51.44443746581286],[0.646562002525377,51.44347279686887],[0.643275359337677,51.44381233522274],[0.643319767259142,51.44348390913273],[0.642820916180399,51.443444773689954],[0.642465429213983,51.443694755289556],[0.643206115076072,51.444207860258885],[0.64293196942041,51.44464488601988],[0.641704404357708,51.44469954354024],[0.641657079968318,51.444453226631765],[0.640283825480999,51.44440143334906],[0.64044333805272,51.44419815086843],[0.641266274328181,51.44436581696307],[0.640778698793675,51.443998109963346],[0.639553897762574,51.443950148093776],[0.638346731077392,51.444432464991195],[0.638615687562641,51.44552739455238],[0.63750534603602,51.44569269854762],[0.638263214245325,51.445505632002934],[0.637474053941891,51.44534978575383],[0.637767217085665,51.444942004350416],[0.637004908904269,51.44515166029267],[0.637147933556048,51.4445862544536],[0.636680214561464,51.44476317755987],[0.636190296858965,51.44445401088986],[0.636257317447855,51.44379315965296],[0.635534014700965,51.44443006357308],[0.635019148487548,51.44441284535513],[0.635493139194303,51.44419531626615],[0.635172489870153,51.444026230221255],[0.635775278110955,51.444020783477875],[0.635645910376287,51.44372415763733],[0.63455049952883,51.44417332526656],[0.635012830718119,51.44407837814598],[0.634853529757037,51.444411189116394],[0.634168959467073,51.44422148693249],[0.63352738914445,51.443527999346664],[0.630385472521102,51.44182926111663],[0.630294998674929,51.44045505485831],[0.631288143897637,51.43998033317735],[0.631810085657945,51.43881997639745],[0.631308871136359,51.43861354064138],[0.630591648498148,51.43715176817136],[0.628485470727333,51.43693996946497],[0.627715711220131,51.43719379745748],[0.627667770588896,51.43688544490467],[0.627275243857378,51.43739344908365],[0.626252575838891,51.43727783470429],[0.625779777248539,51.4376158691357],[0.624905039745262,51.437671418523806],[0.623501513848529,51.43726388914577],[0.623973967888962,51.43651754048039],[0.622495831866206,51.43679168223723],[0.622003544926302,51.43638800759409],[0.621191758689574,51.43638549308978],[0.621174325552894,51.435930742433555],[0.620487542367815,51.435799480586944],[0.619718942649647,51.435118649426784],[0.61996933100551,51.43451490592946],[0.620537572534382,51.43461194172196],[0.621056916796771,51.43400575647792],[0.619634074558877,51.43303193108616],[0.620500250128137,51.43204923493349],[0.620400865005156,51.43164487497893],[0.619132380512329,51.43117941675149],[0.619582246375228,51.43119543045896],[0.619348884707997,51.43101536134132],[0.617869095385283,51.430703918202624],[0.616226314057511,51.42912599861603],[0.616975289216125,51.429340455809225],[0.616755748005114,51.42897386799225],[0.616044163583767,51.42873339132121],[0.61524868052852,51.42924135163324],[0.614136157814712,51.42911145455759],[0.613769117035827,51.42822644904343],[0.614281834082836,51.4275286883868],[0.614088076561611,51.42685750845236],[0.614599979963787,51.42690187566634],[0.6147900776756,51.42645146762293],[0.61451133443566,51.4259035991362],[0.612927555439534,51.42550625256783],[0.612896212310728,51.42515885745337],[0.613626286648542,51.42481696752019],[0.612599702877628,51.424878511489716],[0.611865252718481,51.42421126747179],[0.612242026662153,51.42314866426855],[0.611824542345414,51.422084871001786],[0.609979983370055,51.42109692999757],[0.607051101725468,51.42051894964481],[0.606897234810299,51.41996381006431],[0.607505310445597,51.419551794360316],[0.611645952434781,51.42089524200772],[0.613651743207764,51.422363478138344],[0.614128572604092,51.422122579702716],[0.615278889980907,51.422363213413334],[0.614982322188206,51.422965267293165],[0.615961377125573,51.42338057412796],[0.615661538101974,51.423647227938275],[0.615059218355188,51.42340427021967],[0.614853928254005,51.4236895187642],[0.61557720012533,51.42388387334215],[0.616661694151962,51.42357543319999],[0.617010174840289,51.42378263351131],[0.617046279675036,51.424817136734276],[0.617697483376868,51.42558785108003],[0.618165081283727,51.4273997780384],[0.619985119871142,51.42815156900483],[0.620916847126805,51.42803988503972],[0.621835340412868,51.42744545819077],[0.622168312850407,51.427555852162726],[0.622039774089394,51.42727179385117],[0.622773362376699,51.42706738927556],[0.623020947664823,51.4264654881437],[0.624316301928625,51.42617203393535],[0.62507832924139,51.425559512432024],[0.624791563158549,51.42517554465611],[0.624227116307735,51.42556958304559],[0.624087093258406,51.42498444298682],[0.62489166381676,51.42368375213508],[0.625128841310216,51.42383045544593],[0.626868034949238,51.423048494264684],[0.625942681703566,51.423370587192636],[0.624591364960576,51.42213435045594],[0.62301606306925,51.422009512331165],[0.622371410872825,51.421178404374004],[0.617144490050554,51.41986414991883],[0.614503779342648,51.418689848319325],[0.612351179231011,51.41683990363603],[0.607751597484472,51.41589258298426],[0.60365872898061,51.41565789170647],[0.603163836646601,51.415302805099444],[0.599347081402196,51.41544503827321],[0.599737970973708,51.415768293373695],[0.598671609234186,51.415810810741256],[0.595754617140991,51.4146467155314],[0.593553426699972,51.41420789117998],[0.588879109784293,51.415605529691916],[0.587895256096954,51.41526205628573],[0.586850120724584,51.415400268916066],[0.586941807422527,51.41508791637969],[0.586358778971704,51.415233006604836],[0.586427881878437,51.41500480593205],[0.585802262366857,51.415005983540084],[0.585074417575944,51.4154655096464],[0.583552354078961,51.41548735371752],[0.58244061662425,51.41521050226821],[0.583265124516464,51.41513838594378],[0.581732895419417,51.41505699382252],[0.580621637148282,51.414226030879625],[0.580240551846142,51.41540285683019],[0.579344925595195,51.41536049736597],[0.577245045176347,51.41495601889062],[0.575440481965877,51.41292143930683],[0.574730692969122,51.41280660153101],[0.574697268758084,51.41254468144131],[0.574104843741635,51.412522612338975],[0.574035478389385,51.41302875542025],[0.573287609198047,51.41251805559221],[0.57282082065907,51.41273518957401],[0.572724941777017,51.41230823768592],[0.572236518368377,51.41265265816328],[0.572696072606157,51.41307522418704],[0.571323942976273,51.41271763771821],[0.570694481054404,51.41285556270616],[0.570620711135814,51.41261705551431],[0.570046437805527,51.412841894439104],[0.568968053847849,51.41189948253847],[0.569445808563288,51.41174956452151],[0.568940278010501,51.411634728958134],[0.568951555220009,51.41114338376572],[0.568004820420625,51.411111931528325],[0.56774331105707,51.410808231847824],[0.566964003012662,51.41096741574635],[0.566461873590202,51.4106563810944],[0.561212445168026,51.410714506435696],[0.556805286854319,51.41176774852989],[0.550643061530711,51.41178683235309],[0.548752282166987,51.411540139465735]],[[0.57234919458357,51.4073063302961],[0.574459610700953,51.40493573878666],[0.576293488958444,51.4044799265067],[0.578562829596258,51.40486357755689],[0.577856285220782,51.40498345142],[0.578480480657145,51.405265650921805],[0.578301785339065,51.40505460155629],[0.579208563552184,51.40494021254309],[0.580289516152765,51.405927459392416],[0.580124398775495,51.40634126675616],[0.581147426937823,51.406349332245604],[0.58134203749412,51.40610217905145],[0.580830270696866,51.40597852408006],[0.581448896836834,51.406008086827],[0.581720159377999,51.405666603453284],[0.580877362902197,51.40551245444596],[0.580312532247486,51.40572367202693],[0.580096092449868,51.40540371820222],[0.580766269439802,51.40535299241779],[0.580827570440635,51.404960369950025],[0.580865949445881,51.40525905961866],[0.581289948365766,51.40525422141755],[0.581143936243304,51.404347153342265],[0.582714921193938,51.40458691385155],[0.58311854668449,51.404144434666854],[0.582867193378696,51.403920623275845],[0.583827999955017,51.40359181560585],[0.584255306205478,51.40260016215412],[0.583808626242902,51.402023536197056],[0.582982952520235,51.40189151799481],[0.579210060534756,51.4024881629661],[0.570824639641606,51.40233142195564],[0.565241962916724,51.40163427917122],[0.563200779793823,51.40169962434115],[0.561926318654969,51.4026962140029],[0.562564064004855,51.40417451490499],[0.562507189585248,51.40552409206117],[0.564533109751432,51.406518683687196],[0.56535957684401,51.407435176172065],[0.566116748908771,51.40742129531988],[0.567862005556938,51.407100649408434],[0.57234919458357,51.4073063302961]],[[0.662119115251106,51.44691820924536],[0.66277982349818,51.44620069365889],[0.661772466353155,51.44625505363994],[0.662946602896894,51.4460494033605],[0.662997974784287,51.44527465577852],[0.661923335001364,51.44558240679824],[0.662837361130424,51.44526032432273],[0.662580125906395,51.444302807703565],[0.662905012242601,51.443207040187566],[0.661123886491624,51.443245681438626],[0.660777380592482,51.44364843410924],[0.658688573516332,51.443296446074825],[0.658275772970433,51.44357476376493],[0.658844343903239,51.44372377699754],[0.659139075731194,51.44446097590538],[0.658893143156629,51.445158249968095],[0.658733306938116,51.44481020640678],[0.658499394420253,51.44514470551098],[0.657221906881393,51.44490920991785],[0.657770369854661,51.44545535648122],[0.658725841905692,51.4456477676392],[0.659231232852749,51.44718615354158],[0.660255903484941,51.44740485449043],[0.662119115251106,51.44691820924536]],[[0.539037427604719,51.344081457325295],[0.538252888207645,51.34436023056604],[0.537627242460432,51.344110236329016],[0.538016782327785,51.34341459068308],[0.537254681801679,51.34334564868704],[0.534581426047531,51.34216496831081],[0.532432709660155,51.34085769742428],[0.53145547259111,51.34188715681263],[0.530914072497659,51.34178371306486],[0.531249515119151,51.341928446166236],[0.530356484081883,51.34297492755632],[0.531574227832387,51.3430772924856],[0.531410569740639,51.34326067324089],[0.532119420777974,51.34332815066047],[0.533536775200561,51.34423656584796],[0.532325382542879,51.34495355598486],[0.532851552140593,51.34527498704923],[0.53271342704516,51.34612978650201],[0.532119617734549,51.34622265306419],[0.532506777829181,51.34657588089311],[0.530883164160981,51.34734489547926],[0.530392889932304,51.34712790206269],[0.526411003203955,51.34959739847315],[0.525387371294188,51.349501628915995],[0.525133184013151,51.35012951652751]],[[0.597482494570569,51.365707174507534],[0.60570721038734,51.36426338870568],[0.609093205804565,51.36293769826001],[0.613471688660448,51.3620386261889]],[[0.613471688660448,51.3620386261889],[0.616661714472642,51.36141508188478],[0.613013364351958,51.35858226010727],[0.611386406742214,51.35922751929311],[0.609990751224466,51.35919118466379],[0.606356432391869,51.35712598030378],[0.603117179835301,51.354853082582636],[0.603493169120603,51.35456766067865],[0.603064573024381,51.35364710514267],[0.601936235494672,51.3522168317275],[0.599937054996782,51.35088053676432],[0.600375089464387,51.350650411555925],[0.600076000943308,51.350366546803585],[0.598557518271855,51.34957632639664],[0.596851907011323,51.35152018639343],[0.592804965330217,51.352554370424166],[0.590513120955207,51.347987134028145]],[[0.580603363345031,51.35852848636161],[0.580979256647753,51.365339894683665],[0.581555551191786,51.368074126984844]],[[0.581555551191786,51.368074126984844],[0.584290883075681,51.36788428543055],[0.597482494570569,51.365707174507534]],[[0.63231040309862,51.360370957134634],[0.627700157490816,51.36180751020726],[0.61775676230174,51.36398743510448],[0.617066311118046,51.363445188822894],[0.615746377734165,51.36395861118287],[0.614922044010187,51.36285716568086],[0.613471688660448,51.3620386261889]],[[0.597482494570569,51.365707174507534],[0.599329967444809,51.36828724453591],[0.602039726659968,51.36779892979165],[0.60485343062972,51.370332238184034],[0.589533078415586,51.37845231464874],[0.58451328547805,51.380300915255425],[0.578522486810162,51.381836955156075]],[[0.58406205069202,51.389763434536405],[0.587164896119283,51.38951508949183],[0.588075770671601,51.39031891479464],[0.589242684455809,51.39041277359414],[0.594353460063352,51.389774467745596],[0.594778105702117,51.389530305888584],[0.594325973658821,51.387942843595084],[0.594761668296434,51.3872846542954],[0.594369094374057,51.386571058331796],[0.595041660854026,51.38638976870724],[0.595297431354488,51.38669262799125],[0.596321348895662,51.38591259092967],[0.597890032199095,51.38670445873698],[0.598462947499942,51.38806168947254],[0.599504292209849,51.3887806722535],[0.600072970365132,51.38884541160384],[0.600145725398575,51.3886072294132],[0.601914612822895,51.38909958848996],[0.603828804265753,51.39009867705111],[0.60437369040686,51.38979514457327],[0.604647748555283,51.38884909771465],[0.602999651549059,51.38876334901521],[0.602498214552623,51.38899666360739],[0.600055697486359,51.38818647124553],[0.600035010326799,51.387922490085955],[0.599726790982789,51.388090330113535],[0.598678711661062,51.38765843120326],[0.598382675376923,51.386290569004736],[0.60048239297948,51.385191601970774],[0.600491480967108,51.384185771222896],[0.601311256922429,51.384117216228],[0.601465811204189,51.38390239941625],[0.600997462001053,51.38393257812148],[0.601908719692974,51.383829604541965],[0.603159558623643,51.38287176637967],[0.603978837331599,51.382769013464085],[0.608041677841795,51.38030402848817],[0.609980343715863,51.37976704178926],[0.610585429924072,51.380170943106656],[0.611519296184378,51.38021488885558],[0.613672986741213,51.37888690119431],[0.613485168240803,51.3782902298108],[0.61565289579615,51.37789196179569],[0.617037627775225,51.378179468904236],[0.617974931923496,51.37770429986337],[0.617982817539131,51.37738927720177],[0.618752434209976,51.37790460740826],[0.6179353123748,51.378571393937364],[0.618816196741005,51.37876941162084],[0.61827514990625,51.37840639111365],[0.618968428703489,51.378213708375945],[0.619619437683256,51.37869030710072],[0.619184532594594,51.37897705041348],[0.620208544071873,51.37891279525545],[0.623622141295977,51.38222757447804],[0.623172263594079,51.38340878396761],[0.623585292475133,51.38615468483779],[0.62318824241081,51.38567245146491],[0.623004083758943,51.38654907051034],[0.620909159352813,51.387221077565],[0.620917845438492,51.38795126240375],[0.621879269382452,51.38849823358466],[0.622407905339827,51.388365876362236],[0.622509532715039,51.388634344514635],[0.6231898077957,51.38836276942499],[0.623897458377918,51.388519633625755],[0.626250421950093,51.38801091953313],[0.625973116568618,51.38728495192183],[0.626707423417883,51.387856752881206],[0.626417259039642,51.38743418157208],[0.626837641002658,51.38759567740568],[0.626925753194376,51.38717634637443],[0.626586025052284,51.387067921283275],[0.627264844171158,51.38689710490051],[0.627161477141001,51.387601923621226],[0.627812589122961,51.38787516511253],[0.628012961731682,51.38668155073061],[0.628198389642421,51.38773428674395],[0.633088352236061,51.387721690827654],[0.635504984072252,51.3885461682254],[0.636327706747091,51.38855284097862],[0.636864844819629,51.3877689903857],[0.637381469969285,51.38780324911714],[0.637010312887138,51.38742392592954],[0.637238933824958,51.386100139483624],[0.636244440963087,51.385205947378296],[0.636480097132222,51.385079210661246],[0.634992901363419,51.38391456328769],[0.632132955921451,51.383751273080925],[0.630004734178815,51.38223480927225],[0.629856465107915,51.3816048682675],[0.62649728914414,51.38052701785702],[0.627028661199717,51.37966597982702],[0.625663825813158,51.37892386952725],[0.625842869510118,51.37833609179074],[0.62492336556596,51.37731327213942],[0.624216922106656,51.37549228716866],[0.625296519755868,51.375923265540514],[0.625564318356919,51.37578144495168],[0.625185543932041,51.375516473798406],[0.62558896805989,51.375408495820835],[0.62592643538474,51.375880383844],[0.628613624396525,51.37419294779191],[0.627424434125705,51.372927018204564],[0.627520802163676,51.37087130096178],[0.624978464975452,51.36868401906519],[0.627953489519217,51.36771245394765],[0.6284269256663,51.36815068363702],[0.630068239604406,51.367829603511936],[0.636595205166952,51.36583083040989],[0.63231040309862,51.360370957134634]],[[0.63231040309862,51.360370957134634],[0.630985050519616,51.358679961169045],[0.630255234525175,51.35883129361513],[0.627012356442034,51.3546341937999],[0.623769668470897,51.349148040479264],[0.621718155440325,51.34916789577988],[0.619847406684283,51.348100686608724],[0.619618223667271,51.34685281587633],[0.61540719650171,51.3405767458748],[0.613005463750249,51.338776541445014],[0.613735680796776,51.337399311349834],[0.61263260014772,51.33593167437194],[0.609692465264744,51.33410199678636],[0.605560674775171,51.335715073974136],[0.603711881124019,51.33408224852284],[0.603085486839873,51.3327586202095],[0.601447895419373,51.33198638301065],[0.598622095928229,51.33216518520349],[0.598492675189645,51.33279680620953],[0.596042502731577,51.33268562841263],[0.595404126856575,51.333077613632796],[0.59349817953238,51.33322061395532],[0.588150933392435,51.334546087536374],[0.587790799370752,51.33422034354893],[0.586342198191995,51.33417320776391]],[[0.512437587903931,51.37859019740324],[0.509298091699171,51.38496728113996]],[[0.509298091699171,51.38496728113996],[0.510803267225909,51.386048653912674],[0.508514638272619,51.38907062339651],[0.506892245450107,51.39010828043559],[0.504232409569297,51.39107812616282],[0.50385187904769,51.39087483883192],[0.503384168611129,51.39110341398028]],[[0.503384168611129,51.39110341398028],[0.507063393699821,51.39297666319854],[0.510317705944654,51.393804696492076],[0.511378981313801,51.39294371355248],[0.51188006759924,51.39117459311985],[0.511659458458055,51.39066296476995],[0.510924817482179,51.390320667575615],[0.511841081395376,51.390094180541446],[0.512239994982877,51.388320719084966],[0.510815928878418,51.38764687592528],[0.512805112603462,51.388218629714956],[0.513030035811547,51.387705559277215],[0.512553740685415,51.387434233379885],[0.513176290899119,51.38654290738681],[0.51223398685543,51.386030585514376],[0.513143482768351,51.38583926896236],[0.512694088912275,51.38529747711799],[0.513618480742839,51.38574630417631],[0.51547695924024,51.384589182401626],[0.515266077441215,51.38380927557453],[0.51589857481149,51.38365357072571],[0.516433077279938,51.383964103432405],[0.518977440966647,51.38320684069617],[0.519605668580845,51.38354864810823],[0.520192495484266,51.38331922015446],[0.524219540042895,51.38453591418977],[0.525116016790461,51.3859881906031],[0.524529831457491,51.38711716186104],[0.524701810740995,51.38778627080893],[0.525612276410925,51.38920406480764],[0.527602827851981,51.39523879590505],[0.529867582404984,51.39787112033511],[0.530254653922984,51.39779798593283],[0.530002607390485,51.39802470576431],[0.53072514099571,51.39840217198809],[0.530822572549394,51.399071934824185],[0.532204496023332,51.39922916001043],[0.532142426009994,51.39945896149636],[0.531067566846972,51.399368873345225],[0.532810360864072,51.40210153793377],[0.53496175138241,51.407385177801885],[0.536429914120786,51.408836608411946],[0.538851999907026,51.40977266978861],[0.540462012817232,51.409730578724385],[0.545589578020874,51.40869548136044],[0.549898472814072,51.407064572779454],[0.554925257915136,51.39992394421758],[0.554486249095226,51.39947750384535],[0.555186983485892,51.39925353671293],[0.554340242329383,51.398896023613446],[0.555354801036509,51.39880825314237],[0.555248055227014,51.39797675615821],[0.555533885521112,51.398796243037886],[0.556886136373535,51.398575169218944]],[[0.512361054294713,51.37511816664996],[0.512474583679064,51.369972754707135],[0.511008279418849,51.36717814075531],[0.509817438998495,51.36705346122229],[0.509964004577096,51.365451087319066],[0.507169653764445,51.3658517628571],[0.507302983346902,51.366214103921244],[0.505740466612511,51.366728702356895],[0.5038138879902,51.36575978201725],[0.503178215301538,51.363984346890724],[0.501765827467469,51.363694308654466]],[[0.501765827467469,51.363694308654466],[0.501855681445602,51.36449920394879],[0.500903291411871,51.3643450264784],[0.500726860700531,51.36395484268505],[0.500182330659931,51.36408698552435],[0.501491371632622,51.36825320238743],[0.500674157448739,51.371951223734925],[0.501550733436439,51.37532436055014],[0.504121679353289,51.37911456832728],[0.50369121593612,51.38160357913181],[0.505640597721479,51.38508606835848],[0.507677941762515,51.38438488600697],[0.509298091699171,51.38496728113996]],[[0.525022302772957,51.350489895182825],[0.523436852731513,51.35039091851206],[0.521807504249664,51.350826206050584],[0.521005944041684,51.34988374767438],[0.520431275892808,51.349724288177384],[0.520723347834814,51.34941936629443],[0.51874048950909,51.34877750352184],[0.518434779217345,51.34776138369789],[0.516411051773896,51.346791124051194],[0.514965409698937,51.3448109420683],[0.514447932056806,51.344514415387344],[0.513978328531003,51.34469899570773],[0.513437609681236,51.34431842935149],[0.513014872749752,51.34210491298499],[0.513535035378279,51.34040542211988]],[[0.513535035378279,51.34040542211988],[0.512832475654054,51.3403728186129],[0.509246272106154,51.34275953846139],[0.507517473719746,51.342397179703795],[0.50467784425998,51.34710368203451],[0.503889403517069,51.34826464923587],[0.504768449378015,51.34871178551058],[0.503660654342999,51.35089147292562],[0.504818033429437,51.352595501508965],[0.504763803423292,51.35412846702342],[0.500568602592639,51.353142296662526]],[[0.500568602592639,51.353142296662526],[0.498574160699793,51.35677278597688],[0.498449742635614,51.358366579124926],[0.498746585882774,51.359807452302505],[0.500211340126205,51.359530627618604],[0.500413901746936,51.36008486189822],[0.501325327462546,51.36009420775805],[0.501226858939886,51.36063417849343],[0.502129935932324,51.36038554778998],[0.502802958430496,51.36071387940545],[0.503409587626255,51.36295852526771],[0.501775005913174,51.36304560884952],[0.501765827467469,51.363694308654466]],[[0.500568602592639,51.353142296662526],[0.495740677269232,51.35211564660422],[0.492917589723657,51.35348362500953],[0.491155309973451,51.353808105242585],[0.490670677877385,51.354672033166416],[0.489317739949983,51.355472540980294],[0.483477990832627,51.357145545419506],[0.481327305696754,51.356905129306725],[0.480795802293744,51.35788960030975],[0.477662182030626,51.36001395013897],[0.477349930301363,51.35968507423254],[0.474434506152971,51.3612775955255],[0.472060211465039,51.361690244249765],[0.468347812332227,51.3636439622093],[0.458640121059817,51.367521538789894],[0.465603172390976,51.370216571167596],[0.469378680826211,51.37289475798396],[0.478332507792462,51.37407727335568],[0.481183220692252,51.375048589230545],[0.482023755658024,51.37594822082616],[0.48246869915931,51.375725605817834],[0.482182812695628,51.37617870082747],[0.482996034133586,51.37577558143958],[0.482243614923593,51.376478737455486],[0.482983708053976,51.37727341122413],[0.483989360964238,51.376045024682114],[0.484417044510269,51.37613936898601],[0.483948989416368,51.37673216490339],[0.48428696737332,51.37697502596465],[0.483645871332033,51.377159554941564],[0.483806067973153,51.37817973539079],[0.486802832837891,51.377781419435316],[0.486892267405434,51.377150798479896],[0.484587673304568,51.37645055288579],[0.484814709563294,51.37623705803612],[0.487018877298179,51.37710043254705],[0.487018636731731,51.37783798534458],[0.490645258421722,51.378345440249724],[0.492284014409601,51.37969835996029],[0.493747200906481,51.380040440697336],[0.496830690715408,51.38244903050564],[0.496591959880061,51.3825521640943],[0.498414719506428,51.384137681126724],[0.498505826456101,51.38631427297465],[0.49782260241858,51.38694143345806],[0.502305818045517,51.38993996623029],[0.503384168611129,51.39110341398028]],[[0.50879062748577,51.39632244545929],[0.508324041418353,51.39672906692786],[0.50661062456276,51.39634387286069],[0.505349129652447,51.396702732193226],[0.505320665137143,51.39623472846813],[0.503999732020877,51.39555779763393],[0.503204054100899,51.394836347370216],[0.503268880935188,51.39439062698039],[0.502003191525086,51.39359197124104],[0.502353456860489,51.39342350509832],[0.502135745703882,51.392938863359284],[0.501364862756997,51.39240574216691]],[[0.501364862756997,51.39240574216691],[0.497303060848006,51.39496316870808],[0.496097333070313,51.39531808199618],[0.479650622271216,51.39671099933515],[0.469385156791023,51.398004612307446]],[[0.469385156791023,51.398004612307446],[0.469626530062279,51.39898803519036],[0.471123183509233,51.39917136064651],[0.469880718709463,51.40263887152243],[0.476307010964239,51.4056969820343],[0.479286769933946,51.40665389947783]],[[0.479286769933946,51.40665389947783],[0.485057504525841,51.40903024734669],[0.489334168596488,51.40719177452592],[0.493673441996576,51.40828046332945],[0.494960284060467,51.405393677907185],[0.499047890040798,51.405850712747494],[0.499499200630073,51.4039719757633],[0.501577145159192,51.404075151089344],[0.505506946940434,51.403381323451974],[0.507377684927644,51.402324941017035],[0.510148462979864,51.399586104423186],[0.50879062748577,51.39632244545929]],[[0.548752282166987,51.411540139465735],[0.547415594789227,51.41150626944223],[0.539599386891673,51.41300720968158],[0.536663284184936,51.41287115585847],[0.534062862088617,51.41212059787231],[0.531927640374366,51.41091019169937],[0.530522797969419,51.409302574898874],[0.52803097192765,51.40485458895387],[0.527750271652822,51.403622985494394],[0.528198245061234,51.40306194172735],[0.527796355570412,51.402031752212096],[0.525224450594272,51.399956418593085],[0.524411307983683,51.39997035574426],[0.524588015097954,51.39926320466207],[0.523243616542084,51.399056514769846],[0.522158292167541,51.3992453830599],[0.518548142543078,51.40056431062626],[0.518332601004949,51.401012371937455],[0.517348223578732,51.40128628684125],[0.516860619124818,51.40102242521727],[0.517879123617085,51.400085790094856],[0.516112065617487,51.39995917438287],[0.5178589666174,51.399222801787595],[0.517864708244553,51.398778380907686],[0.518512476137401,51.3985027062644],[0.518298532607675,51.39796048607225],[0.519203875840181,51.398106506438666],[0.518740436486858,51.397654182995076],[0.519703356057748,51.39733214735419],[0.519357899932896,51.39701221096156],[0.519579452387851,51.397327631360426],[0.518846058606776,51.39711768544276],[0.519355865671589,51.39663540629036],[0.520797099644811,51.3970351878638],[0.521472008858302,51.39691453067883],[0.521380224354083,51.397206106975005],[0.521758487532394,51.397129599531496],[0.52235524797023,51.39770406190231],[0.521794532404708,51.39846263262616],[0.523113306027559,51.397604961957796],[0.522373994675908,51.39700030712063],[0.52276148287199,51.3957597417361],[0.522264452525935,51.39391497226191],[0.522674313937455,51.39318570173106],[0.522528558593277,51.39009372867505],[0.520871480930309,51.38654658623518],[0.520101759142999,51.38635176780212],[0.519292908284176,51.386517621598195],[0.516725880932063,51.38817772067328],[0.51261530955411,51.394121560417055],[0.510384464199616,51.39594203717594],[0.50879062748577,51.39632244545929]],[[0.479286769933946,51.40665389947783],[0.477673659409422,51.40825848929958],[0.477176864775199,51.408114268929005],[0.476811159384462,51.412416022818846],[0.482575574834018,51.41426556959754],[0.485351291333304,51.41221799767299],[0.489955462593467,51.41367544469502],[0.490908134471047,51.414794796061926],[0.490233022020983,51.41891251014469],[0.492869529912103,51.42424517653307],[0.492192915336578,51.42455371747074],[0.491828815677963,51.42531790700368],[0.491292474363552,51.42540306851092],[0.490884588341248,51.426500097174795],[0.491059444038473,51.42950147815056],[0.490154725421888,51.42969255523279],[0.490037567631886,51.429998145904335],[0.490529581889689,51.43441307549531],[0.488029984751387,51.43549697148499],[0.49143297412731,51.43705092506141],[0.492646931039175,51.438148547777985],[0.489590652147114,51.439848726655754],[0.489633726697933,51.442756712397205],[0.487764196010225,51.44297000390442],[0.486037523463092,51.444222706241284],[0.484462062497659,51.44439190818977],[0.482798302501654,51.44516295507641],[0.481866794615675,51.44502529532834],[0.481560790246041,51.4455138736081],[0.480584395999944,51.44584936072216],[0.478994124084298,51.44572020253414],[0.478520935507616,51.44612595024281],[0.477437489522159,51.44623971067449],[0.471472998279069,51.45005344402328],[0.471299968122877,51.4507145552529],[0.470424112622567,51.45067637329355],[0.469267989411258,51.453818299294404],[0.467725633420177,51.45426182227873],[0.467279085154272,51.45380349602411],[0.463786864369134,51.45402358803957],[0.462405893532781,51.45545938713588],[0.461059227765977,51.45609120390287],[0.460738008059433,51.45595404602593],[0.460972500593662,51.45501455562418],[0.460515541903277,51.45516448223464],[0.460605276917817,51.454638229159585],[0.460190231141443,51.45473687504221],[0.460296462260812,51.45582838507709],[0.458887914956292,51.45664857692396],[0.460306509892371,51.45866326064124],[0.459125765825089,51.460294479457126],[0.457903633151477,51.460513502433514],[0.456892659334777,51.462250867540696],[0.455981613526503,51.46292838190026],[0.457566353308156,51.46457803806006],[0.460021307506048,51.46548445882668],[0.461807093304726,51.46490009946196],[0.462187658252307,51.464453152102536],[0.464267228369058,51.46448500722899],[0.467617738180401,51.46405473644484],[0.468719535035463,51.46352513039262],[0.469290738775535,51.46367680833805],[0.468469112397526,51.46534104080467],[0.465990527158812,51.46568012907368],[0.461838036270028,51.465555143362906],[0.461163784524611,51.465895815212185],[0.460010904060794,51.46590651630479],[0.459546205489635,51.46642267872617],[0.460901121541136,51.469709635599074],[0.463163968095718,51.47177583745674],[0.462828310019734,51.47319052569395],[0.463641751421129,51.47494809004531],[0.467649909877248,51.478600163108524],[0.468567893699674,51.47871487266883],[0.468929857767828,51.48024262189362],[0.470416800648579,51.48224859266805],[0.483166239754876,51.48664031795618],[0.489781042979581,51.486760898911186],[0.494436308590605,51.48605843594761],[0.505939979221132,51.485223099900196],[0.511083427589119,51.484917897218644],[0.515432874661018,51.485132290343586],[0.516683112780158,51.484945346898414],[0.517672124061493,51.48441053559156],[0.523556458568114,51.48424624723207],[0.527745462225037,51.483696412956206],[0.532345756816968,51.48461623315859]],[[0.501364862756997,51.39240574216691],[0.499945480537403,51.3917649890275],[0.497525645977019,51.39221151791828],[0.495532807997296,51.393292875467935],[0.495223621441656,51.39308000432743],[0.497783306316264,51.391741911082185],[0.496717943955338,51.39102795962277],[0.495718814977309,51.391293943903975],[0.494746377967269,51.39078128978026],[0.493625448824234,51.39116137521304],[0.49428579373993,51.390666064855516],[0.494245494704264,51.39008315435828],[0.494834590820473,51.38997077059955],[0.494009471339637,51.389919999651525],[0.494381610153407,51.389598149929455],[0.493293313238928,51.38943965760221],[0.491963305617995,51.387980261435615],[0.492168072598245,51.38563458524125],[0.493365779925856,51.38383886949725],[0.492616109315174,51.38244992318745],[0.491458534940931,51.381409651682965],[0.488925039587646,51.381210839355134],[0.487369751681869,51.381661294287184],[0.483022161019094,51.38100982620162],[0.477952427885282,51.37887940786165],[0.476200544156359,51.377259685346765]],[[0.458377500878594,51.39375252930318],[0.455583102427826,51.396501411173936],[0.453521154914422,51.3977885714595],[0.458385449209609,51.398057163941075],[0.469356667948653,51.39776869468219],[0.469385156791023,51.398004612307446]],[[0.581555551191786,51.368074126984844],[0.578672024806118,51.36897774857854],[0.566873277742966,51.37093597719045],[0.567534409943794,51.372735683511614],[0.568038795366747,51.37709956506219]],[[0.539007537253399,51.33333417022228],[0.534604416925419,51.336623609947736],[0.527314441662912,51.334176119431795],[0.526165955191949,51.33459756408347],[0.52546440913017,51.33533944564408],[0.523930266349855,51.33587712539987],[0.523409193936153,51.33692453362057],[0.522029613828851,51.33768999335086],[0.521631395556946,51.33864932858306],[0.52122516312505,51.33862569972566],[0.521004593676956,51.33939498847071],[0.518343247496146,51.33912566843941],[0.516478614579848,51.339925779932344],[0.515809710215441,51.34058686603902],[0.513535035378279,51.34040542211988]]],"bbox":[0.399005643117822,51.327354330005136,0.725183472497706,51.486760898911186]}
