{"type":"Topology","objects":{"E08000010":{"type":"GeometryCollection","geometries":[{"type":"Polygon","arcs":[[0,1,2,3,4,5,6,7]],"properties":{"objectid":6426,"cmwd11cd":"E36006426","cmwd11nm":"Abram","cmwd11nmw":null,"lad11cd":"E08000010","lad11nm":"Wigan","lad11nmw":null,"st_areasha":12995317.84766086,"st_lengths":19424.90520037862}},{"type":"Polygon","arcs":[[8,9,10,-4]],"properties":{"objectid":6427,"cmwd11cd":"E36006427","cmwd11nm":"Ashton","cmwd11nmw":null,"lad11cd":"E08000010","lad11nm":"Wigan","lad11nmw":null,"st_areasha":5834723.41114321,"st_lengths":15594.304247024565}},{"type":"Polygon","arcs":[[11,12,13,14,15]],"properties":{"objectid":6428,"cmwd11cd":"E36006428","cmwd11nm":"Aspull New Springs Whelley","cmwd11nmw":null,"lad11cd":"E08000010","lad11nm":"Wigan","lad11nmw":null,"st_areasha":20077201.729892787,"st_lengths":28141.888190751797}},{"type":"Polygon","arcs":[[16,17,18,19]],"properties":{"objectid":6429,"cmwd11cd":"E36006429","cmwd11nm":"Astley Mosley Common","cmwd11nmw":null,"lad11cd":"E08000010","lad11nm":"Wigan","lad11nmw":null,"st_areasha":17658265.53299568,"st_lengths":24706.544607287866}},{"type":"Polygon","arcs":[[20,21,22,23,24,25]],"properties":{"objectid":6430,"cmwd11cd":"E36006430","cmwd11nm":"Atherleigh","cmwd11nmw":null,"lad11cd":"E08000010","lad11nm":"Wigan","lad11nmw":null,"st_areasha":5705592.943200895,"st_lengths":12517.53533911035}},{"type":"Polygon","arcs":[[26,-26,27]],"properties":{"objectid":6431,"cmwd11cd":"E36006431","cmwd11nm":"Atherton","cmwd11nmw":null,"lad11cd":"E08000010","lad11nm":"Wigan","lad11nmw":null,"st_areasha":4746535.792613635,"st_lengths":13615.47541910866}},{"type":"Polygon","arcs":[[-5,-11,28,29,30,31]],"properties":{"objectid":6432,"cmwd11cd":"E36006432","cmwd11nm":"Bryn","cmwd11nmw":null,"lad11cd":"E08000010","lad11nm":"Wigan","lad11nmw":null,"st_areasha":6805829.211759145,"st_lengths":14832.06270741655}},{"type":"Polygon","arcs":[[32,33,34,35,36,37]],"properties":{"objectid":6433,"cmwd11cd":"E36006433","cmwd11nm":"Douglas","cmwd11nmw":null,"lad11cd":"E08000010","lad11nm":"Wigan","lad11nmw":null,"st_areasha":3789637.561841755,"st_lengths":11956.611095959997}},{"type":"Polygon","arcs":[[38,39,-9,-3,40]],"properties":{"objectid":6434,"cmwd11cd":"E36006434","cmwd11nm":"Golborne and Lowton West","cmwd11nmw":null,"lad11cd":"E08000010","lad11nm":"Wigan","lad11nmw":null,"st_areasha":8147633.789512705,"st_lengths":16284.89510148268}},{"type":"Polygon","arcs":[[41,42,-8,43,-12]],"properties":{"objectid":6435,"cmwd11cd":"E36006435","cmwd11nm":"Hindley","cmwd11nmw":null,"lad11cd":"E08000010","lad11nm":"Wigan","lad11nmw":null,"st_areasha":5020409.22634124,"st_lengths":13933.163765118315}},{"type":"Polygon","arcs":[[-24,44,-1,-43,45]],"properties":{"objectid":6436,"cmwd11cd":"E36006436","cmwd11nm":"Hindley Green","cmwd11nmw":null,"lad11cd":"E08000010","lad11nm":"Wigan","lad11nmw":null,"st_areasha":4208944.163412205,"st_lengths":12104.50844105726}},{"type":"Polygon","arcs":[[-44,-7,46,-34,47,-13]],"properties":{"objectid":6437,"cmwd11cd":"E36006437","cmwd11nm":"Ince","cmwd11nmw":null,"lad11cd":"E08000010","lad11nm":"Wigan","lad11nmw":null,"st_areasha":4773353.38969371,"st_lengths":11492.929125014103}},{"type":"Polygon","arcs":[[-18,48,49,-22,50]],"properties":{"objectid":6438,"cmwd11cd":"E36006438","cmwd11nm":"Leigh East","cmwd11nmw":null,"lad11cd":"E08000010","lad11nm":"Wigan","lad11nmw":null,"st_areasha":4973361.92200318,"st_lengths":11058.906592860965}},{"type":"Polygon","arcs":[[-49,-17,51,52,53]],"properties":{"objectid":6439,"cmwd11cd":"E36006439","cmwd11nm":"Leigh South","cmwd11nmw":null,"lad11cd":"E08000010","lad11nm":"Wigan","lad11nmw":null,"st_areasha":6520687.189033255,"st_lengths":12363.79994303987}},{"type":"Polygon","arcs":[[-23,-50,-54,54,-41,-2,-45]],"properties":{"objectid":6440,"cmwd11cd":"E36006440","cmwd11nm":"Leigh West","cmwd11nmw":null,"lad11cd":"E08000010","lad11nm":"Wigan","lad11nmw":null,"st_areasha":7333407.66200862,"st_lengths":16164.746847124097}},{"type":"Polygon","arcs":[[-53,55,-39,-55]],"properties":{"objectid":6441,"cmwd11cd":"E36006441","cmwd11nm":"Lowton East","cmwd11nmw":null,"lad11cd":"E08000010","lad11nm":"Wigan","lad11nmw":null,"st_areasha":11182505.324963765,"st_lengths":17991.641656414657}},{"type":"Polygon","arcs":[[56,57,-30,58,59]],"properties":{"objectid":6442,"cmwd11cd":"E36006442","cmwd11nm":"Orrell","cmwd11nmw":null,"lad11cd":"E08000010","lad11nm":"Wigan","lad11nmw":null,"st_areasha":8885156.78719261,"st_lengths":19663.962937802597}},{"type":"Polygon","arcs":[[60,-37,61,-57,62]],"properties":{"objectid":6443,"cmwd11cd":"E36006443","cmwd11nm":"Pemberton","cmwd11nmw":null,"lad11cd":"E08000010","lad11nm":"Wigan","lad11nmw":null,"st_areasha":6230872.39189915,"st_lengths":12655.370401642402}},{"type":"Polygon","arcs":[[63,-63,-60,64,65]],"properties":{"objectid":6444,"cmwd11cd":"E36006444","cmwd11nm":"Shevington with Lower Ground","cmwd11nmw":null,"lad11cd":"E08000010","lad11nm":"Wigan","lad11nmw":null,"st_areasha":8958573.04698867,"st_lengths":17463.055064610973}},{"type":"Polygon","arcs":[[-15,66,67,-66,68]],"properties":{"objectid":6445,"cmwd11cd":"E36006445","cmwd11nm":"Standish with Langtree","cmwd11nmw":null,"lad11cd":"E08000010","lad11nm":"Wigan","lad11nmw":null,"st_areasha":10401936.66427711,"st_lengths":16020.332557720274}},{"type":"Polygon","arcs":[[69,-19,-51,-21,-27]],"properties":{"objectid":6446,"cmwd11cd":"E36006446","cmwd11nm":"Tyldesley","cmwd11nmw":null,"lad11cd":"E08000010","lad11nm":"Wigan","lad11nmw":null,"st_areasha":5559564.60738928,"st_lengths":12895.68169879077}},{"type":"Polygon","arcs":[[-48,-33,70,-67,-14]],"properties":{"objectid":6447,"cmwd11cd":"E36006447","cmwd11nm":"Wigan Central","cmwd11nmw":null,"lad11cd":"E08000010","lad11nm":"Wigan","lad11nmw":null,"st_areasha":3532875.20603199,"st_lengths":9564.75119294131}},{"type":"Polygon","arcs":[[-71,-38,-61,-64,-68]],"properties":{"objectid":6448,"cmwd11cd":"E36006448","cmwd11nm":"Wigan West","cmwd11nmw":null,"lad11cd":"E08000010","lad11nm":"Wigan","lad11nmw":null,"st_areasha":2710484.783828255,"st_lengths":9167.644768806984}},{"type":"Polygon","arcs":[[-36,71,-31,-58,-62]],"properties":{"objectid":6449,"cmwd11cd":"E36006449","cmwd11nm":"Winstanley","cmwd11nmw":null,"lad11cd":"E08000010","lad11nm":"Wigan","lad11nmw":null,"st_areasha":6183305.96779143,"st_lengths":10268.036728670093}},{"type":"Polygon","arcs":[[-47,-6,-32,-72,-35]],"properties":{"objectid":6450,"cmwd11cd":"E36006450","cmwd11nm":"Worsley Mesnes","cmwd11nmw":null,"lad11cd":"E08000010","lad11nm":"Wigan","lad11nmw":null,"st_areasha":5938222.5514988,"st_lengths":11357.766195161757}}]}},"arcs":[[[-2.569156469375475,53.5209476836846],[-2.567399576290865,53.520417552716985],[-2.566461618709253,53.51964442915068],[-2.566325909519825,53.51716392414976],[-2.565674099494573,53.51601542579683],[-2.558714159075768,53.515045915123586],[-2.556761957009177,53.514202835452785],[-2.554762524308311,53.514470202563444],[-2.550549164668579,53.51428742215696],[-2.547789469446219,53.51490066048878],[-2.548324240607152,53.51356773320746]],[[-2.548324240607152,53.51356773320746],[-2.548287434631893,53.51281906497006],[-2.549959514133346,53.512781700103766],[-2.550103820420935,53.512396268372854],[-2.552672736036428,53.51277993856862],[-2.555140729095087,53.51190907550407],[-2.556567991673809,53.510917169690856],[-2.557608341862226,53.511127141766956],[-2.561310679322155,53.50758671397441],[-2.561776188283261,53.507553977416826],[-2.561244297461605,53.50621789897536],[-2.561566675126174,53.50425751477136],[-2.563547394661716,53.50193876019432],[-2.564994953358362,53.49922508653625],[-2.566523411488882,53.4988600415225],[-2.570093040264869,53.49870369416204],[-2.571567876788361,53.49962528123364],[-2.576385086628618,53.501515104759996],[-2.57659504019127,53.5009900267631],[-2.579445095647833,53.501237784362864],[-2.580652464549281,53.50099099128708],[-2.581035756099844,53.501236346145674],[-2.586205569108395,53.49869581109727],[-2.581017558838179,53.4964845390762]],[[-2.581017558838179,53.4964845390762],[-2.580743315513091,53.49616317147852],[-2.581167766298043,53.495781739194136],[-2.593168857274519,53.491192067052765],[-2.595081104552317,53.48942334726817],[-2.59715858259495,53.494705083303714]],[[-2.59715858259495,53.494705083303714],[-2.597918461693137,53.496531494315185],[-2.599878466831355,53.49653877257093],[-2.600053744247144,53.49763281032114],[-2.603073466565935,53.49698744718561],[-2.605140184495745,53.49749569624601],[-2.604456682474768,53.49830819565001],[-2.605952384507299,53.4990494454686],[-2.607855210773841,53.500636319197305],[-2.612935526403497,53.50130526459685],[-2.61201025233217,53.50301441945737],[-2.615391174594048,53.503346728171444],[-2.614896396271357,53.50416823091465],[-2.61701210183579,53.50479830611818],[-2.618571980687698,53.50474347964629],[-2.618433414455427,53.505579315202674],[-2.622528788844053,53.506385987093836],[-2.622569251421735,53.50667704812738],[-2.624308398958063,53.507114758897146],[-2.625048959248869,53.5078417078134],[-2.625465771241997,53.50911245381199],[-2.6237102946741,53.51013385485958],[-2.624817259354047,53.5103393140286],[-2.630425439818419,53.51009772016869],[-2.63179822898447,53.51032687912646]],[[-2.63179822898447,53.51032687912646],[-2.626723500930386,53.514326126755606]],[[-2.626723500930386,53.514326126755606],[-2.616740275360315,53.52223598136524],[-2.614319043889502,53.524635193019385],[-2.613871756787705,53.526677269074064],[-2.615607967875664,53.529052407420615]],[[-2.615607967875664,53.529052407420615],[-2.615421756515182,53.53046923516016],[-2.614531729881961,53.53162897066958],[-2.614183526816011,53.53102576281247],[-2.612180432922574,53.53117808908915],[-2.610177180003881,53.52984799634068],[-2.608654191207127,53.530543468693956],[-2.608481161541826,53.53142085371761],[-2.608985806781298,53.53199363767209],[-2.605420219190641,53.533259525402535],[-2.605055288366568,53.53423132874249],[-2.604299314427784,53.53465405698061],[-2.600319564218022,53.535361850246645]],[[-2.600319564218022,53.535361850246645],[-2.599691976467772,53.53483552826066],[-2.597490906376107,53.535193571585445],[-2.596106426171732,53.53417208274036],[-2.592427036703759,53.53325997183422],[-2.592240227014431,53.532523729047185],[-2.591227898833453,53.53188239876135],[-2.59135391143408,53.531287547520755],[-2.590728127850663,53.53087982654033],[-2.590638155856572,53.53027168357313],[-2.591094549145854,53.5298900511251],[-2.590680449523739,53.52918908339037],[-2.589851332522617,53.52880396044031],[-2.588556382577917,53.52887867429045],[-2.584874806037717,53.526887577283176],[-2.581343591343034,53.52384113686956],[-2.579695751685499,53.521813889229364],[-2.569156469375475,53.5209476836846]],[[-2.59715858259495,53.494705083303714],[-2.598672981051272,53.49433789663977],[-2.601953792297631,53.49415062687283],[-2.602807039655089,53.49383082916725],[-2.603510036323338,53.49397110405728],[-2.604259247135231,53.49344052561859],[-2.606454475934814,53.49314174778683],[-2.607794338442327,53.4894339855371],[-2.608724690025365,53.48998030994706],[-2.611165944796522,53.4882535739068],[-2.608466951179974,53.486615086706706],[-2.608585012634451,53.48286318941921],[-2.609965466066315,53.48254242135912],[-2.608432346122772,53.48167286981784],[-2.608361112972119,53.48038144995557],[-2.610743593338223,53.480895192872715]],[[-2.610743593338223,53.480895192872715],[-2.612572308801423,53.480943348603745],[-2.61452317804139,53.481513151333026],[-2.617390939516733,53.4815990793219],[-2.629701638008395,53.480630501294144],[-2.631755027968384,53.48078328167556],[-2.63602162970696,53.480186252076805],[-2.644149362879582,53.480009725931126],[-2.644141546012081,53.48048711269348],[-2.646613038053999,53.48196423228325],[-2.650522334951916,53.48510644181273],[-2.651487233662817,53.485221651369166],[-2.651636278987215,53.48619349470112],[-2.652673667414447,53.48621930401388],[-2.654525625805299,53.490098025699545]],[[-2.654525625805299,53.490098025699545],[-2.652206969372338,53.49037225710821],[-2.650442029170304,53.48989555289387],[-2.647048270652382,53.490051495395356],[-2.644838489622557,53.488269115967064],[-2.639047097145825,53.488252556124884],[-2.637902562926932,53.48802043299335],[-2.63759994567772,53.48844364283209],[-2.636989452766655,53.488443285734924],[-2.640460483137864,53.49261386577578],[-2.63495962533521,53.49240764146493],[-2.630092701174163,53.49266351384911],[-2.630567341724444,53.49376220697045],[-2.629643348066303,53.493263683610145],[-2.62892682544771,53.49353893411937],[-2.629170846855947,53.49423613830832],[-2.630711925087876,53.49456419091025],[-2.630673656283677,53.495539772208794],[-2.629078074079268,53.49794654818486],[-2.626601396051777,53.49981408221162],[-2.630402310751214,53.50163241627667],[-2.627536937175028,53.50363779053215],[-2.634260766157787,53.505464914698706],[-2.635211218618249,53.507004241525216],[-2.635697354989933,53.5071418904907],[-2.63179822898447,53.51032687912646]],[[-2.567929451989284,53.54738217292945],[-2.567749939871277,53.547052221881],[-2.568734984884963,53.54689650855026],[-2.569063842223897,53.54610025803974],[-2.569343876495991,53.54649626350227],[-2.56874493656526,53.54853616061013],[-2.569315075839033,53.54839234255088],[-2.574679230572118,53.54892574759354],[-2.574610947256156,53.54812241056748],[-2.575353486055458,53.54800555124592],[-2.579373708440585,53.54915836888699],[-2.57948804611418,53.548800902837904],[-2.580722667230887,53.54857198429347],[-2.583771559175402,53.54703067752672]],[[-2.583771559175402,53.54703067752672],[-2.584459086553517,53.547519926162934],[-2.586407610206192,53.54805784285305],[-2.585754732892927,53.55094489290472],[-2.584233468033496,53.55282752849223],[-2.588128144392614,53.553691108432794],[-2.586642039801798,53.5545155672508],[-2.590234559733554,53.55567453042792],[-2.59180234045406,53.55572609030819],[-2.598391495114988,53.551418789463455],[-2.60267306314966,53.54986724474729],[-2.60407041291952,53.55036896530734],[-2.610688399170039,53.54797820200767],[-2.6110893073621,53.54919420932542],[-2.612217023334578,53.54909852114445],[-2.612345145237164,53.54929652816424],[-2.615418410138811,53.54867122025249],[-2.618189145364463,53.54914226716796]],[[-2.618189145364463,53.54914226716796],[-2.612354440739505,53.55484197125735],[-2.614160556889347,53.55789530439466],[-2.616998751010265,53.55902316617853],[-2.618087623702327,53.559146981904235],[-2.621444579215888,53.55805618745528],[-2.622938729676737,53.55801872414581],[-2.62313532329539,53.55752688288212],[-2.623507572671792,53.55809844574026],[-2.622058682222479,53.559057973370535],[-2.622228752023473,53.56035964182759],[-2.623240613945081,53.560889243132664],[-2.623310962598986,53.56187321242],[-2.62395076279309,53.56225548446841],[-2.626225052000234,53.562382886063126],[-2.627565997243366,53.563102190523296],[-2.627735981770821,53.56367210581114],[-2.627153666485335,53.564526459671804],[-2.627854225903045,53.56625236040262],[-2.629411756616302,53.5679252135662],[-2.631591206496039,53.56845755612129],[-2.631464402324225,53.569576561823105],[-2.632255653280252,53.56997778272021],[-2.63289746877554,53.57169862485236],[-2.632538893831843,53.57226329092755],[-2.633193452311655,53.572910670097905],[-2.632539177679345,53.573903906585954],[-2.634120323343938,53.57510467296941],[-2.635460152219724,53.57480901857143],[-2.63728988307893,53.5734445712356],[-2.638150931222394,53.57214817343205],[-2.638489589571272,53.57227132915402]],[[-2.638489589571272,53.57227132915402],[-2.638665425334387,53.57853802645882],[-2.640395537280232,53.58628515590096],[-2.645416051964701,53.59702079379468],[-2.648347761948054,53.59622923176905],[-2.651787722881928,53.5957745976929],[-2.651491064661708,53.596335383638895],[-2.652038573287578,53.59724935436366],[-2.654295439402901,53.59699977169929],[-2.654807161347065,53.59725499627761],[-2.65659538004727,53.598262832530025],[-2.65610636308944,53.59840038150311],[-2.656815607040671,53.60048031548854],[-2.658162583167381,53.60070127917384],[-2.658226849330238,53.60094726531493],[-2.65740901629226,53.60103173762968],[-2.657976557461342,53.60341990035788]],[[-2.657976557461342,53.60341990035788],[-2.65747083521526,53.603944986753916],[-2.653746410526112,53.60422239376242],[-2.651173040358076,53.605640566918524],[-2.64870129973408,53.60590835367075],[-2.64633739155233,53.60650810223462],[-2.645551660123875,53.607022031478095],[-2.642350810776736,53.60696098848478],[-2.64033652711823,53.60729985455486],[-2.639992608839501,53.60704820421072],[-2.638945575169275,53.60737916924687],[-2.637854068120558,53.60716653863613],[-2.635210869422069,53.60750233944686],[-2.634764292184696,53.60806297253214],[-2.633195147113895,53.60805506747126],[-2.63191094138981,53.60728515086642],[-2.630699552671021,53.6070371163846],[-2.630969862077168,53.60631113142442],[-2.630094869646939,53.60581321299489],[-2.629886135838333,53.60498992601751],[-2.630807259820504,53.60330491530553],[-2.63036461903527,53.60301508396549],[-2.629981141988587,53.599685518181026],[-2.628436113719032,53.5989358091136],[-2.626649520269728,53.59686855325934],[-2.626834768319417,53.59508761646265],[-2.626097862214226,53.59502134651947],[-2.624509253468845,53.59345376335564],[-2.626830579255478,53.591327244363484],[-2.627218737033839,53.590189808453616],[-2.62616736853752,53.58918398328786],[-2.622350854856245,53.5893908732684],[-2.619354012476653,53.59017143071686],[-2.618517206712705,53.59070256831927],[-2.616662897171636,53.59088472065134],[-2.614910523384474,53.59049194095555],[-2.611073996449991,53.590264358004475],[-2.606315416015986,53.58884302407988],[-2.604849402780719,53.58806747095375],[-2.60185651823486,53.58796928489569],[-2.60030038045558,53.588612662699404],[-2.594691659792402,53.588586795691576],[-2.594018172243023,53.58785298524648],[-2.587414674739842,53.58613271994785],[-2.583684862442173,53.5848367571002],[-2.582154620983994,53.583960561694795],[-2.58078247366472,53.58260177059948],[-2.576786554026861,53.58113257461518],[-2.57616046496505,53.5806358049382],[-2.576562546863763,53.57976458617827],[-2.576311443235757,53.579180577707845],[-2.577681298884265,53.57816804696443],[-2.577148041063513,53.577274368453715],[-2.573658891515668,53.576489385418114],[-2.571918628282719,53.574000521951604],[-2.570804805753903,53.57383415292058],[-2.570739651487226,53.57348297784741],[-2.567205473512821,53.57189169310369],[-2.567141310274485,53.57138498199707],[-2.566449871781056,53.57128940933653],[-2.564329651883682,53.569821614534675],[-2.564277340603162,53.56849684293343],[-2.56579513791946,53.56737133250676],[-2.566661559100331,53.565418356384626],[-2.566358450355239,53.56522562761497],[-2.567068752351315,53.56448063595593],[-2.563044400575085,53.56344257930142],[-2.562548661421967,53.562951401555985],[-2.561446829877129,53.56286758520051],[-2.559986689983284,53.561953084465806],[-2.55865834611865,53.5618666973538],[-2.558229943357311,53.56086459582489],[-2.561744560136625,53.560043560893405],[-2.561976323775713,53.559305345357046],[-2.561212307959545,53.5587291357059],[-2.560877492729218,53.55727530817835],[-2.559861592851147,53.55637483198343],[-2.558785889662554,53.55597353609641],[-2.55841964552706,53.55533071394549],[-2.55978613152126,53.55455121011202],[-2.559645585101126,53.553055987557514],[-2.561242656766181,53.55259722357155],[-2.561162658104483,53.551686955993546],[-2.562292855017319,53.55154048208947],[-2.562666780609656,53.55093912302087],[-2.565542779892729,53.55051922684642],[-2.565208857071112,53.54992566702174],[-2.56678795709717,53.54960626380482],[-2.566385148499418,53.5489456460452],[-2.568136392305795,53.54773088211354],[-2.567929451989284,53.54738217292945]],[[-2.494925838557318,53.4806848234111],[-2.495063908606093,53.48089551669354],[-2.48807577709476,53.482342030317476],[-2.481357238276801,53.48421136367961],[-2.475975477897653,53.48625745253538],[-2.470287056814044,53.48896624246596],[-2.472216443800796,53.48883361987415],[-2.473393827558299,53.49277278354838]],[[-2.473393827558299,53.49277278354838],[-2.472343393781945,53.493065545822155],[-2.471884064054841,53.49486889558944],[-2.471263411397396,53.49490644296535],[-2.471803138806246,53.495860803183106],[-2.469632909100628,53.496059948273384],[-2.469939709004614,53.497764106977385],[-2.46720537459511,53.49849314750617],[-2.466184880680174,53.49920105591011],[-2.466909178990226,53.49939240332087],[-2.469317655600567,53.50163756939445],[-2.468006867381367,53.502820390914216],[-2.468259975406208,53.50376243231249],[-2.470370142727667,53.50381705263734],[-2.470144132361496,53.505331797701075]],[[-2.470144132361496,53.505331797701075],[-2.462739509389672,53.50470633141975],[-2.461724748015662,53.50484873623183],[-2.462287888402524,53.50587947191496],[-2.460994874839093,53.5062377881423],[-2.459296098015494,53.50615624850839],[-2.458027729233667,53.50725605470689],[-2.457794544137192,53.50814515678145],[-2.458344691495525,53.5092389058156],[-2.457410977137521,53.50991762600354],[-2.453690569314009,53.50991475777775],[-2.452970263220731,53.509544433270314],[-2.451787338254507,53.51005231764799],[-2.447104758969658,53.50976699151822],[-2.445079576836933,53.509925558096036],[-2.441586077349542,53.50955470727086],[-2.440523778193187,53.509792316616775],[-2.440232390745417,53.51033910642817],[-2.440638955856326,53.511880215857175],[-2.441990597992147,53.51191030046726],[-2.441979795968753,53.51217821852817],[-2.440619210573311,53.51215626695651],[-2.440587431332182,53.51258252127879],[-2.433164084608576,53.51242175561822],[-2.433360074300736,53.51330111524054],[-2.432420847582867,53.51333957798713],[-2.43225842991082,53.51472094584647],[-2.436648962137889,53.515015163792114],[-2.437051884589164,53.5176782068833],[-2.435978214863806,53.51888667177626],[-2.434705512661101,53.51818384164348],[-2.434224269761177,53.51980366967943],[-2.432818321623876,53.51979348808167],[-2.433263843007063,53.52044178299554],[-2.434034256144612,53.52069880361515],[-2.430948991077031,53.5221491170164]],[[-2.430948991077031,53.5221491170164],[-2.425724362498768,53.52133534014636],[-2.423997823818142,53.5206474729182],[-2.421410827466544,53.52019540003898],[-2.416906496029171,53.51787390005054],[-2.413161901585445,53.51468031614542],[-2.41434354606541,53.513197533488956],[-2.413928790731923,53.51180289193132],[-2.418033404135222,53.51189384686371],[-2.417295174116037,53.51012189881255],[-2.420822177930329,53.508863617336864],[-2.419904664985182,53.50803530639155],[-2.420753898391308,53.50729427374747],[-2.41908732937367,53.506508143897655],[-2.429053196840784,53.50454543533444],[-2.428705073465857,53.501574687230445],[-2.431687569514756,53.500844753135304],[-2.431689686257641,53.499421689010134],[-2.430293040399083,53.4977348645408],[-2.432205074441578,53.49688023186583],[-2.434031264998916,53.49427106535661],[-2.437076991731578,53.492127593202916],[-2.436871216349713,53.49161320655024],[-2.434929244925144,53.49039501207414],[-2.434255590408677,53.48805023833447],[-2.434291195400646,53.48696144212791],[-2.435137174897532,53.48626794060372],[-2.435313364854528,53.4846347663892],[-2.437163094571524,53.48189326244559],[-2.434783997794155,53.471641009089474],[-2.433105342692093,53.46482024404331],[-2.437039624116463,53.46446517423629],[-2.463711662482735,53.461984941106145],[-2.475335391067099,53.46215955561265],[-2.477749140841054,53.461532359116894],[-2.479557205428112,53.461571844875614],[-2.481316212709665,53.46100112497356],[-2.48210933076049,53.460400164684174],[-2.48530597996016,53.46015437911805],[-2.486621874976572,53.46049604769478],[-2.488321659880535,53.45989488842101],[-2.488453901337207,53.46197090230149],[-2.490861766897916,53.46490775964734],[-2.489715593434123,53.46729109943091],[-2.489678456443086,53.46877901320302],[-2.490268418565197,53.46963959176174],[-2.489988594063004,53.471901599062946],[-2.489029689618319,53.47290160012636],[-2.48772841446597,53.47557863401807],[-2.491333208236883,53.47913190552216],[-2.494925838557318,53.4806848234111]],[[-2.486625873472611,53.51601476138669],[-2.487621692678839,53.513025228247415],[-2.488427338534171,53.51212919572188],[-2.48715489157472,53.51085426452648],[-2.487063095793058,53.50968868524559]],[[-2.487063095793058,53.50968868524559],[-2.492009585231899,53.50904267427403],[-2.496108459609448,53.50775455247438],[-2.503215583300574,53.50635021161868],[-2.504323240423527,53.50591491420716],[-2.505683643312888,53.50453820331171],[-2.506159687758495,53.504626987562304],[-2.506136027654452,53.50681791979459],[-2.510965597054395,53.505779663873845],[-2.516796080361593,53.504979610360614],[-2.516696018671004,53.5041925445231]],[[-2.516696018671004,53.5041925445231],[-2.5198699717176,53.503812843459976],[-2.521814779998179,53.50428171182792],[-2.526017117747095,53.50414817592998],[-2.525529348413619,53.50615866712557],[-2.52746854554757,53.5061573026517],[-2.527800593134356,53.50594095703777],[-2.528720666423139,53.50728893803628],[-2.527634532950101,53.508955950807724],[-2.528237636711602,53.5093092712581],[-2.528030189995378,53.509726422004924],[-2.528585875949259,53.5099019733502],[-2.528176177297223,53.51042967583373],[-2.529346383024696,53.51090723456995],[-2.527924168699671,53.511021410516086],[-2.526912935471043,53.51192934069536],[-2.52764604847623,53.51303181278351],[-2.526541727208786,53.514340200968306],[-2.528526570989643,53.515669989276155],[-2.527385572749604,53.51621889965353],[-2.527718465105196,53.516545579171],[-2.526562700200635,53.51712151282727],[-2.526710602148308,53.51749124075467],[-2.525249777533656,53.51852517977839],[-2.525490983514865,53.51972959858533],[-2.531893704650286,53.51992415373415]],[[-2.531893704650286,53.51992415373415],[-2.531700303543951,53.52086257021279],[-2.532284366674392,53.5208815206509],[-2.531526174873688,53.52176680407373],[-2.531147632214487,53.522015689805926],[-2.528939318160831,53.522026417962074],[-2.529914793659316,53.52270888489409]],[[-2.529914793659316,53.52270888489409],[-2.527575286016532,53.522847810634175],[-2.527566656156682,53.52312205431573],[-2.527122959759582,53.523108720223256],[-2.526836407809101,53.52347854704393],[-2.527294508132079,53.52368058147943],[-2.526709561762639,53.52371015940931],[-2.526549931750599,53.52446057583915],[-2.526068764787693,53.524466292256584],[-2.526390463852868,53.525344046447884],[-2.52527713010773,53.52522675214614],[-2.523981994412654,53.526142140162584],[-2.521758527739947,53.52640990559813],[-2.521328247723636,53.526873857152616],[-2.520368515030039,53.52685737845953],[-2.519794986237315,53.52733005034371],[-2.51958376356522,53.52696239267826],[-2.519152947535701,53.527014605109805],[-2.518271211266704,53.527700738675506],[-2.51740666272537,53.527694629050835],[-2.516927626109804,53.52824955806113],[-2.515796115654009,53.52825267859165],[-2.51440684455686,53.529020995080295]],[[-2.51440684455686,53.529020995080295],[-2.513416550295215,53.528481405440054],[-2.512087380406563,53.52947866479963],[-2.508833764039809,53.52854421589251],[-2.507942245517726,53.52302578134047],[-2.503728173437867,53.52436155030811],[-2.503268466392082,53.52287214310725],[-2.501203569424508,53.52328176243042],[-2.499389588703282,53.52130449681449],[-2.496522872570258,53.52305774710759],[-2.493546919837008,53.523478268514296],[-2.488844890101872,53.52336100800642],[-2.487391701131205,53.52267116853416],[-2.485844116654965,53.52242038806959],[-2.485322753610069,53.52167997090066],[-2.485760902699005,53.52160807568401],[-2.485588524941773,53.519862072855936],[-2.486702917241479,53.51851990662597],[-2.486625873472611,53.51601476138669]],[[-2.452697561805764,53.525982141035946],[-2.464561995260422,53.52794128328573],[-2.470502656758573,53.5284205346252],[-2.470001732697081,53.52801166174261],[-2.470137532861365,53.52747088614212],[-2.469510506866832,53.52683957562909],[-2.469637100789877,53.526145089639414],[-2.469020997900824,53.52500405525692],[-2.470862333677802,53.52426142087],[-2.470848214713803,53.523671738719],[-2.471227698272114,53.52361005195063],[-2.470449593494481,53.52159939761574],[-2.470499813315414,53.520684949578374],[-2.471053262541669,53.5202647612513],[-2.470819640543351,53.51932895512613],[-2.472151541185159,53.51838424972031],[-2.473037446092122,53.518425678183476],[-2.474403457101773,53.517968979397224],[-2.474539008188253,53.51822013511378],[-2.482068699850178,53.51688733326177],[-2.481901809436821,53.516401645502626],[-2.483599484893651,53.51594530100455],[-2.486625873472611,53.51601476138669]],[[-2.51440684455686,53.529020995080295],[-2.513979030927327,53.530816247536386],[-2.514609532082781,53.53191653410901],[-2.51474207376538,53.533634771500864],[-2.514421826984502,53.53422585614468],[-2.513873756211977,53.53420034908765],[-2.514122713733631,53.53556663190669],[-2.511654147994409,53.536082464933486],[-2.508712328287489,53.533881825957145],[-2.507855435944383,53.53439970161575],[-2.507653478100386,53.53542986285884],[-2.506563373957201,53.53626154439258],[-2.50589978426909,53.53756250235062],[-2.505602238817849,53.538551751800675],[-2.503833488997199,53.53867161659212],[-2.503836290270082,53.53839742936895],[-2.502220634474225,53.53832244053022],[-2.500769847507501,53.53763545676955],[-2.497800525138536,53.53781153100463],[-2.496658850645858,53.53722746373301],[-2.494987276762361,53.536879318114906],[-2.495059363584889,53.53646190084862],[-2.488752221360861,53.53533368599959],[-2.488330605656749,53.534364558571085],[-2.485714563335563,53.53388353438843],[-2.480571627037916,53.53317443722522],[-2.476978405490212,53.53326708445236],[-2.471004561786364,53.53149834385363],[-2.468041539886839,53.531808512213466],[-2.464651553103809,53.5304714765181],[-2.46013269214589,53.53047723590468],[-2.454578212403912,53.529167152973365],[-2.449698376744359,53.52841250707168],[-2.449729162944055,53.52804199914552],[-2.452697561805764,53.525982141035946]],[[-2.654525625805299,53.490098025699545],[-2.655341663469916,53.4922815740957],[-2.658530160096522,53.49200426838833],[-2.661541671409317,53.49255941336413],[-2.65998453910214,53.49343905603707],[-2.662483048216687,53.49443927595938],[-2.66349203228865,53.49572095504116],[-2.663418316292726,53.4965016479471],[-2.664932672726713,53.499528093198826],[-2.667104021178512,53.499926819641296],[-2.668227729407716,53.49966707948138],[-2.668286376224861,53.49927568032974],[-2.670215432009593,53.49884327964811],[-2.671885094423377,53.498883405984934],[-2.672453292002626,53.49915526640517],[-2.673499680200313,53.498778120139],[-2.676373545596431,53.49860189252896],[-2.678799430919196,53.49898011632116],[-2.678796371086478,53.49925967642587]],[[-2.678796371086478,53.49925967642587],[-2.678799512994506,53.50049212150635],[-2.679639345075261,53.502372427910906],[-2.68003492998174,53.50664108526399],[-2.684360463309461,53.510046841381886],[-2.680077749990846,53.51044341041033],[-2.679888570301396,53.511436932680446]],[[-2.679888570301396,53.511436932680446],[-2.675261988675552,53.51051377987975],[-2.670362695178478,53.50911466257916],[-2.666526721115472,53.50760876305688],[-2.662643597992296,53.505489057163985],[-2.661158124956108,53.50789565073587],[-2.658933498633544,53.51001414995109],[-2.655577116295219,53.51181248460614],[-2.65076443381009,53.513376855389396],[-2.650904451372507,53.51385252025025]],[[-2.650904451372507,53.51385252025025],[-2.645506005380923,53.51541270275273],[-2.643026729605922,53.515537568053794],[-2.641526251839371,53.51595823410789],[-2.636015565012766,53.514899082911434],[-2.632009522663719,53.51692679749924],[-2.626669959692632,53.515194803933255],[-2.626723500930386,53.514326126755606]],[[-2.636204600945518,53.545376108628744],[-2.632821560772118,53.54351618724995],[-2.628667929089962,53.54188690189639]],[[-2.628667929089962,53.54188690189639],[-2.6269689955507,53.541203657512796],[-2.624620773685433,53.53947025491866]],[[-2.624620773685433,53.53947025491866],[-2.626396955412784,53.53884695127023],[-2.628109944963797,53.53895567776085],[-2.62951653222072,53.53794051941009],[-2.631591583439931,53.53733084546511],[-2.635932044532247,53.53472960740176],[-2.637775030135016,53.53566725467388],[-2.639621376625147,53.53572209760608],[-2.640137862636017,53.536149025152866],[-2.639610416599888,53.53659773655676],[-2.641295239650272,53.53784540372335],[-2.641253743490488,53.53829690289773],[-2.644300415506886,53.540370538097605],[-2.646213627591895,53.540737739438924],[-2.648320973745189,53.538096903703014],[-2.650227895226191,53.53657810230432],[-2.657373076352977,53.5333532872224],[-2.662530450709927,53.531408331473195]],[[-2.662530450709927,53.531408331473195],[-2.666211048914468,53.53057530905786],[-2.670913448919777,53.53006098475345]],[[-2.670913448919777,53.53006098475345],[-2.671490161731569,53.530847042115354],[-2.672492160343603,53.530808603801475],[-2.672539621308521,53.53137691488405],[-2.675031833316,53.533537516172565],[-2.674511733850002,53.533755310742684],[-2.675068312585555,53.53421960844835],[-2.673857015242697,53.53471996775414],[-2.674468924406204,53.53524511705161],[-2.674211567253447,53.53595132162697],[-2.674989919695976,53.53612407486184],[-2.674285707573948,53.536631433991964],[-2.674418137373711,53.537272520495904],[-2.676359367315071,53.53731106586062],[-2.675919948821723,53.53786099886073],[-2.676268718354523,53.53787431549087],[-2.676229652343839,53.53826288874988],[-2.674374280792202,53.538219384558055],[-2.674780814036957,53.5389218758167],[-2.672674344275303,53.539224974009535],[-2.671900372249872,53.53885533513056],[-2.671006916719666,53.539426680093186],[-2.669684521980852,53.53969115126268],[-2.669324118661452,53.53817213362097],[-2.669066809241996,53.539370993320574],[-2.669433761911498,53.53996134457783],[-2.66853007299308,53.53997987548818],[-2.668147758894256,53.541003220395794],[-2.667512468114496,53.54129620640261],[-2.666939703405317,53.54326810647579],[-2.664327067508303,53.54471101558732],[-2.664335170737278,53.545903901636976],[-2.663279672694109,53.54664956696776],[-2.660419111222623,53.54672916776214],[-2.659480197188396,53.546919539822134],[-2.659530997507289,53.54717721071927],[-2.65751768458248,53.54670553088523],[-2.657374179468726,53.54630717555632],[-2.655548107738273,53.54652122438186],[-2.654822037234135,53.546908144376346],[-2.654520846818002,53.54724870628059],[-2.654901899053715,53.54729427530695],[-2.654947291796165,53.548376364331084],[-2.654436219733829,53.549397640679736],[-2.660146181322073,53.552090206751366],[-2.660691192604785,53.55267605297688],[-2.66040596454843,53.55404313648311]],[[-2.66040596454843,53.55404313648311],[-2.652982957755886,53.55158372764],[-2.639975634182246,53.54601669764236],[-2.636204600945518,53.545376108628744]],[[-2.556115024208925,53.49234470867502],[-2.558357409223539,53.490453649251435],[-2.562595862500261,53.489971676189846],[-2.5647005749349,53.48897649327232],[-2.565547046930922,53.48756832964419],[-2.564649509884259,53.48512566502395],[-2.564939675656309,53.481891673192024],[-2.566907412484858,53.48083242108725],[-2.569984218474332,53.4800006341808],[-2.569715739596234,53.47919557800761],[-2.570276350868283,53.47942034696864],[-2.573094928732949,53.478227449144974],[-2.573648926762651,53.47829760604603],[-2.575822148148349,53.47652794082461],[-2.578601670599283,53.47514902597088],[-2.579001498365365,53.47541048802495],[-2.579917914164477,53.474872937194256],[-2.579573550247035,53.4747029303243],[-2.580661452138696,53.473707929056964],[-2.580323613001354,53.473574713395244],[-2.582990393156505,53.471688318058774],[-2.582655534075016,53.47078023761346],[-2.583676406847561,53.47084179276608],[-2.584274020030404,53.4693771617281],[-2.583532886472073,53.46905628149756],[-2.584126476736231,53.468943729430606],[-2.584887983547318,53.46745942294973],[-2.595771904514672,53.468579675167284],[-2.598326395646059,53.46081531643732]],[[-2.598326395646059,53.46081531643732],[-2.599455312972522,53.460972370360054],[-2.602099065992509,53.4606642179758],[-2.605429199356993,53.46127752804396],[-2.607706966137243,53.46076439262428],[-2.607721789765959,53.461063652631324],[-2.608836052003086,53.461351020321004],[-2.611988239664782,53.46162529017585],[-2.612300842775646,53.46241208060991],[-2.613449709404296,53.46310915634363],[-2.614096666957846,53.46357600036579],[-2.613763257035907,53.46479488428688],[-2.61536690115971,53.4659938873932],[-2.61449404683769,53.46783047407041],[-2.613718040427055,53.46761152861958],[-2.613092920573751,53.46835096964583],[-2.613499441965828,53.46843695895614],[-2.613154559687037,53.470117058329365],[-2.609842800322483,53.469688118264024],[-2.609269938113254,53.47029604254581],[-2.607594345482434,53.47007175365166],[-2.606909849060333,53.470144435499286],[-2.6064686324499,53.47058357231847],[-2.610477567847584,53.47475672245916],[-2.61065629310865,53.476499771411675],[-2.607739936058851,53.47583055902042],[-2.607952457226673,53.476465926166114],[-2.610776072941392,53.47707360067382],[-2.610814795935694,53.477461714724754],[-2.611793469765868,53.47792959873732],[-2.610845090851688,53.4782059286376],[-2.610743593338223,53.480895192872715]],[[-2.581017558838179,53.4964845390762],[-2.576826600638479,53.494941585423426],[-2.568010573263083,53.49292157062006],[-2.566397693866183,53.49281960763655],[-2.559397261680949,53.49341442496157],[-2.556115024208925,53.49234470867502]],[[-2.567929451989284,53.54738217292945],[-2.566217524938178,53.547812815531984],[-2.565140255363969,53.547164374767476],[-2.561564392213998,53.54715431633719],[-2.558216811991157,53.546138885254564],[-2.556616105936906,53.5442423703943],[-2.55796398721825,53.543562720476714],[-2.557747778259962,53.54216047760152],[-2.55903317445408,53.541440677930765],[-2.559300114011391,53.540626757864096],[-2.56024133576089,53.54024836537102],[-2.560530799230553,53.53896869114154],[-2.559049013081351,53.537833949734534],[-2.55548787998141,53.53785057432315],[-2.555399517330198,53.53755523431022],[-2.555064825887539,53.5376952216848],[-2.553979980865936,53.53712853247691],[-2.553082121047323,53.53713179428746],[-2.5522971779719,53.5359505647749]],[[-2.5522971779719,53.5359505647749],[-2.553124452270581,53.53470529469708],[-2.552648403420389,53.5343029772207],[-2.553047557815644,53.53320710397254],[-2.557182010692167,53.53310425517779],[-2.558323072527144,53.533356895426216],[-2.559827676438004,53.53200413130056],[-2.564363002758802,53.53334740015361],[-2.568148996795161,53.529868412323026],[-2.572419872581912,53.53106881039957],[-2.573237551045096,53.530503025157955],[-2.573868838162837,53.529545298814455],[-2.573732589830097,53.52872785119958],[-2.572470252171426,53.527194031676636],[-2.569793137806092,53.527138518939154],[-2.56841491524256,53.526740549341596],[-2.566980284842097,53.52584389871741],[-2.565203594414719,53.52587749359728],[-2.56457611356312,53.524297412031444],[-2.563293058205183,53.52401580782592],[-2.564122253127497,53.5206821204551],[-2.569156469375475,53.5209476836846]],[[-2.600319564218022,53.535361850246645],[-2.591527690172131,53.53791026994254],[-2.59194732639906,53.538351356196266],[-2.58663553105625,53.53999754481139],[-2.577594094789506,53.54163639484322],[-2.583188491742446,53.54338192854491],[-2.584958718634323,53.54435674694397],[-2.582808054765313,53.54545589432286],[-2.582405752765987,53.54517740825285],[-2.581770268893464,53.54583224687396],[-2.584228302847594,53.54654838267443],[-2.583771559175402,53.54703067752672]],[[-2.531893704650286,53.51992415373415],[-2.54043200962457,53.520088860799255],[-2.540750827642353,53.51989327520874],[-2.539329713178847,53.5189333290352],[-2.539821183004263,53.518912213937675],[-2.539979860725155,53.51763408021519],[-2.541424797312631,53.517392899007355],[-2.541285771676784,53.51536546770902],[-2.539387380882431,53.5155242355779],[-2.538439888436381,53.514076668377115],[-2.536709862922131,53.51383099558436],[-2.536796875038265,53.51319951941147],[-2.541724863624623,53.51313766963791],[-2.542274162150905,53.51398648294908],[-2.543417319153508,53.51398217724094],[-2.543969127105209,53.51361288045914],[-2.54432239200459,53.51375689614467],[-2.544035511709457,53.51431824200456],[-2.545628594470719,53.51399902511056],[-2.545729495375297,53.51363357056094],[-2.54647567260755,53.51372544409844],[-2.546726866468383,53.513436624375736],[-2.548324240607152,53.51356773320746]],[[-2.5522971779719,53.5359505647749],[-2.550676723456604,53.53584929912837],[-2.549563671020117,53.535313262221486],[-2.549654951160453,53.53501709064888],[-2.549170302434312,53.53487904980616],[-2.549022287494798,53.53521869163669],[-2.548590775642295,53.534639925728996],[-2.547896041919607,53.534708714322804],[-2.547689669645286,53.53426829947168],[-2.543590907277112,53.533164200581055],[-2.543861982170555,53.53277194088281],[-2.542358188724211,53.53233917448139],[-2.541090480715126,53.53031148928072],[-2.540221440620548,53.53019406438386],[-2.539993923077175,53.53045578938475],[-2.539301785744594,53.529417926248044],[-2.538302267859578,53.529243544446],[-2.5383873572244,53.52869572073153],[-2.537142939680869,53.52836150716979],[-2.537218445854454,53.528009671470485],[-2.536824257393891,53.52821552733023],[-2.535798291028054,53.52785244393988],[-2.535935361653184,53.52759654615353],[-2.534859989768456,53.52738109064326],[-2.535295219165494,53.52684340706466],[-2.534683381795209,53.5266591554635],[-2.534555022162812,53.52593335853264],[-2.533742473159595,53.52574015221347],[-2.534030322527138,53.52559680687912],[-2.533172817421123,53.524470661775645],[-2.533632625089489,53.523966992789425],[-2.532353962356174,53.52377677089778],[-2.532324755208044,53.52277367789657],[-2.531493873551698,53.5227962585711],[-2.531453405463047,53.52305981930549],[-2.530879251723594,53.52262638310392],[-2.530270814758277,53.523070483938945],[-2.529819569476905,53.52305632687244],[-2.529914793659316,53.52270888489409]],[[-2.615607967875664,53.529052407420615],[-2.619296710609816,53.533383384249845],[-2.62139902676959,53.5330964839761],[-2.621731977543428,53.534093486026926],[-2.620082643263326,53.534399631898275],[-2.624620773685433,53.53947025491866]],[[-2.628667929089962,53.54188690189639],[-2.626851770858877,53.54399819775871],[-2.625357245543218,53.54387658387286],[-2.625426841097279,53.544916321808294],[-2.622154138055868,53.54612274493428],[-2.619591352876811,53.54747825850009],[-2.618189145364463,53.54914226716796]],[[-2.473393827558299,53.49277278354838],[-2.476061697491893,53.492339640348554],[-2.484866840219777,53.49327145034258],[-2.4877357104351,53.49407064899355],[-2.493249882794269,53.4949550239165],[-2.495326274205585,53.49332105939924],[-2.498370900176571,53.49378663747138],[-2.498986037264403,53.494949141161186],[-2.500411161122919,53.49435342100119],[-2.501664721700054,53.492890908919144],[-2.508641233890279,53.495151071011634],[-2.512094351859866,53.49459599478303],[-2.512736970007095,53.49250667634552],[-2.518924716160397,53.49358744812648]],[[-2.518924716160397,53.49358744812648],[-2.517420696336633,53.497091019857365],[-2.517707847697525,53.499127795980876],[-2.516658325251033,53.50208728323993],[-2.516696018671004,53.5041925445231]],[[-2.487063095793058,53.50968868524559],[-2.486829525520791,53.508785250349234],[-2.482638883740834,53.51025862497356],[-2.476708893229701,53.51118056013268],[-2.476553093090369,53.508318847496234],[-2.472385902614513,53.5067793270482],[-2.470144132361496,53.505331797701075]],[[-2.494925838557318,53.4806848234111],[-2.501297023647147,53.47948238169569],[-2.535042506533539,53.47125895060464]],[[-2.535042506533539,53.47125895060464],[-2.531973033349994,53.48980907851198],[-2.531052076211631,53.49138188517903],[-2.527573909730862,53.49522159576015]],[[-2.527573909730862,53.49522159576015],[-2.52460129059057,53.4943887909507],[-2.518924716160397,53.49358744812648]],[[-2.527573909730862,53.49522159576015],[-2.529670836692314,53.4955764161621],[-2.53166608460314,53.49551359226358],[-2.535972624518428,53.49331696088174],[-2.540670746136405,53.49290653287381],[-2.544037982351512,53.491693769223815],[-2.546097345449808,53.49135713007331],[-2.552554761769443,53.49132923579256],[-2.556115024208925,53.49234470867502]],[[-2.535042506533539,53.47125895060464],[-2.549082947605113,53.467816235701875],[-2.551237186933888,53.46756805768484],[-2.547674183843113,53.46123970864764],[-2.568991060978433,53.4582293784269],[-2.569152921611383,53.45647744698643],[-2.572350028491025,53.45095162604656],[-2.573233109136803,53.447748061474265],[-2.57534523776251,53.44580963450789],[-2.577534273894174,53.447227524570735],[-2.581120637767463,53.44796165218463],[-2.581921757929296,53.448624784120376],[-2.582512143791007,53.45149403332242],[-2.583338878199723,53.451928702322554],[-2.581752249295692,53.45308169538716],[-2.58258055058444,53.45363139125186],[-2.585307669441839,53.45492065827664],[-2.586959928094245,53.45525323971661],[-2.587263686052943,53.45587473771042],[-2.591661054631015,53.455509654676604],[-2.594708633848341,53.45620738020194],[-2.597421490026607,53.458053784376524],[-2.598120454173982,53.459344763750025],[-2.59782935947808,53.46071260635113],[-2.598326395646059,53.46081531643732]],[[-2.700032545259762,53.56071096526661],[-2.701011208332002,53.55734038695877],[-2.700808111012692,53.55363247441468],[-2.69700073371395,53.545991024052526],[-2.695798488455048,53.54087485920009],[-2.69591490679287,53.53756690383582],[-2.697020792500524,53.53258113013771]],[[-2.697020792500524,53.53258113013771],[-2.697198199733498,53.52932404047357],[-2.696575266725921,53.52547020893359],[-2.69465670354195,53.519953520875546],[-2.693231429691683,53.517653201369846],[-2.691104815063357,53.515623922776435],[-2.687767914806059,53.513631232324926],[-2.68406040732651,53.512300428440625],[-2.679888570301396,53.511436932680446]],[[-2.678796371086478,53.49925967642587],[-2.68051261963291,53.49975965975871],[-2.68052830044498,53.500173067608436],[-2.681191271556992,53.50005242780862],[-2.681885749802806,53.50067234474383],[-2.683668144626805,53.500871651440136],[-2.684514673975917,53.50063307464569],[-2.686906624229613,53.5012324537881],[-2.688888406383998,53.501080813197916],[-2.689735434197164,53.50161710881282],[-2.691568621738015,53.50196881189629],[-2.693120371095516,53.50179712355222],[-2.695159346911911,53.50200734807916],[-2.695370212159212,53.501625872723],[-2.697507995350652,53.501792310141084],[-2.697644559963059,53.50276237440468],[-2.699334296557558,53.50437691254532],[-2.701763515795727,53.50373885004325],[-2.70243796467476,53.5048585821639],[-2.704076468529935,53.50454957823066],[-2.704610829510693,53.50512896320223],[-2.70416365015492,53.50535005496577],[-2.70436826764434,53.505595166330366],[-2.704878902212316,53.50538089805747],[-2.705688291640797,53.50644677927679],[-2.707115009757252,53.51316261831176],[-2.708622809733915,53.51440417594481],[-2.712872093243583,53.51236795207641],[-2.714197003715528,53.51044167191186],[-2.716134267665514,53.51075910573493],[-2.716877931600682,53.51139563363065],[-2.717799980802876,53.511609492443846],[-2.718273753929406,53.511087017087384],[-2.719165045955833,53.5113522511353],[-2.719756811661174,53.51085336321921],[-2.720646108203367,53.51073831795541],[-2.721644589633416,53.5097650027514],[-2.722395743763537,53.510128157111296],[-2.721896882011198,53.51085752026971],[-2.722123776711119,53.51151780710367],[-2.725375175053419,53.51460408987402],[-2.726002840221056,53.517620879246486],[-2.72707765552239,53.518023414823574],[-2.729138979990475,53.52036350490618],[-2.724850598772961,53.5235548675953],[-2.723494322879394,53.524169842867835],[-2.719560457653981,53.524824620855576],[-2.718343444535786,53.525474711103975],[-2.717212683538146,53.52685692013975],[-2.716541786029659,53.52697510168702],[-2.716705198810357,53.52852304149226],[-2.715802963777386,53.52941934270522],[-2.715347458551842,53.532029076077535],[-2.715692512255695,53.53262572284445],[-2.71491286042145,53.53354821764245],[-2.715617690005521,53.53400700894348],[-2.714867757037645,53.534994974586915],[-2.715191243413863,53.53502716013691],[-2.714997005624747,53.53765330586628],[-2.713404395849705,53.53780212464386],[-2.713174583096979,53.53804533739266],[-2.71451677157238,53.539159249746085],[-2.714663801363901,53.54027311482058],[-2.715385884299943,53.54040455321082],[-2.71722355022337,53.54332601423996],[-2.716317295078567,53.54418003769659],[-2.716530535369225,53.54438463294405],[-2.714720567809873,53.54535372561708],[-2.711182716270215,53.54860376306154],[-2.709486736082384,53.549456163001665],[-2.708760677108266,53.550540112214804],[-2.708877390931933,53.55283265255583],[-2.707800231562423,53.5540508415959],[-2.706391737053376,53.554416894622484],[-2.705693920963298,53.55694078659023],[-2.704576873448634,53.55776809653643],[-2.704257818948141,53.55865096513662],[-2.703432544847324,53.55895967746042],[-2.703932296172751,53.56096505334957],[-2.703351387831595,53.5616283125321]],[[-2.703351387831595,53.5616283125321],[-2.702639734715714,53.561051736179444],[-2.700759825483554,53.56058986774057],[-2.700032545259762,53.56071096526661]],[[-2.674071366370768,53.556708987969245],[-2.66040596454843,53.55404313648311]],[[-2.670913448919777,53.53006098475345],[-2.682860162912659,53.53062735223743],[-2.683798293720517,53.53107235354309],[-2.686551657266891,53.5312445231353],[-2.690767835485777,53.53257417155925],[-2.693511217658528,53.533050958518764],[-2.695320375783567,53.5331420753685],[-2.697020792500524,53.53258113013771]],[[-2.700032545259762,53.56071096526661],[-2.698275034629444,53.56089382091311],[-2.691390472330792,53.55898197280434],[-2.674071366370768,53.556708987969245]],[[-2.652470683253739,53.56727428760868],[-2.65139683148763,53.56509919929991],[-2.650712439420957,53.564683086434435],[-2.651298377666492,53.56350497114597],[-2.653232608598628,53.56320681692792],[-2.653487828809363,53.56281705295843],[-2.656311867840269,53.56215801183037],[-2.65967664471635,53.56083877609649],[-2.662714999750191,53.56019007461122],[-2.663680524446018,53.55917159062704],[-2.663345679445287,53.558613380950455],[-2.663677221717486,53.55828341242386],[-2.662956012191598,53.55792783831544],[-2.663404274138137,53.557241261612354],[-2.666458040147407,53.55826891178554],[-2.668588609656761,53.55828495824322],[-2.669003679741827,53.55875549329856],[-2.671781735284659,53.559708140062774],[-2.673208475780536,53.55941790922662],[-2.674664055951087,53.558094537325225],[-2.673986919172103,53.557474477931606],[-2.674071366370768,53.556708987969245]],[[-2.703351387831595,53.5616283125321],[-2.702826949863031,53.56241799821042],[-2.70382073245012,53.56325271817691],[-2.706547775030926,53.563979279455076],[-2.708133312298231,53.5638000236576],[-2.709883623658762,53.56453581820627],[-2.709657593313776,53.56546671289947],[-2.711208273157737,53.56725819448947],[-2.711004800680364,53.568094538512305],[-2.712921007639064,53.56853446389534],[-2.714273324743224,53.57001242469832],[-2.714386723334036,53.5708271135801],[-2.71627419975704,53.5723279483109],[-2.714220256033185,53.57484648445325],[-2.71629339644315,53.57579243897842],[-2.717837119822187,53.5758838792032],[-2.71637801648456,53.57677718203493],[-2.715609816740073,53.577800305337675],[-2.71504315058663,53.577338023400095],[-2.713415928406441,53.578122606347826],[-2.71311109787498,53.578767212400365],[-2.713557403372303,53.580425795631186],[-2.712988458617103,53.581448603560496],[-2.710258305438822,53.58259573855021],[-2.709020409006872,53.58481629391874],[-2.708314393281425,53.58533020756977],[-2.706812281520469,53.58566629658848],[-2.70609280658356,53.58646520156503],[-2.704607189400114,53.58643621277254],[-2.703304398002304,53.58686371188698],[-2.701373095277235,53.5870170641435],[-2.701133508035496,53.58860963734602],[-2.700346659415203,53.589181462378455],[-2.701424870439955,53.58960128209281],[-2.700016151293251,53.59039252472227],[-2.698533336534305,53.59054140234429],[-2.69868115624935,53.590984610499014],[-2.696792893344407,53.59110438186723],[-2.695373240070523,53.59003836396379],[-2.692836993214761,53.58915316775817],[-2.691986790577746,53.589179632572694],[-2.692269435566923,53.59159354851947],[-2.691199029552582,53.59591204578603]],[[-2.691199029552582,53.59591204578603],[-2.690408686092149,53.5959093829878],[-2.690327965819507,53.5954109171125],[-2.685721123259931,53.59133359966669],[-2.684827376389059,53.5913800558808],[-2.684723388366475,53.59083676981759],[-2.683329381377279,53.59087435938064],[-2.682892769932723,53.59003542118186],[-2.679462735274989,53.590302974410896],[-2.681091265999306,53.58953593741288],[-2.681828991465299,53.588617461638215],[-2.683337583207329,53.58828887093479],[-2.684642564545412,53.587606320585245],[-2.685456144242254,53.587838994804756],[-2.686422644892545,53.58594470618172],[-2.686006822448064,53.58573583562573],[-2.686256556801207,53.584923551502634],[-2.685915693818932,53.58448948924898],[-2.683924105410652,53.583715140211645],[-2.681213435034985,53.5832154191435],[-2.679787075277603,53.582351532855945],[-2.679099973361347,53.58142223563219],[-2.679996287518722,53.580039061754576],[-2.680224125607027,53.57813913165952],[-2.679103700771102,53.577312996564004],[-2.679065650038255,53.576444817218075],[-2.677873040787514,53.57544288345555],[-2.677453700861733,53.5744384039166],[-2.67824080515884,53.573977275739054],[-2.678738621209439,53.57309076993631],[-2.678732164394656,53.57183762052004],[-2.67933184999531,53.57174882155448],[-2.679053743649237,53.57031924603923],[-2.677045721411052,53.57054543772448],[-2.67287483875031,53.570380987583405],[-2.668266444055255,53.56803429754912],[-2.66654088713493,53.56826501901132],[-2.663924402092004,53.57110321307761],[-2.662172646076755,53.572081062982626],[-2.659852316551021,53.5713692817563],[-2.65824908893161,53.5700475825742],[-2.658727493025693,53.569733887158],[-2.657810276845251,53.56911415107191],[-2.65614626057694,53.56873845931724],[-2.655711629183405,53.56797583438404],[-2.652797294595986,53.56700998933804],[-2.652470683253739,53.56727428760868]],[[-2.638489589571272,53.57227132915402],[-2.638851529314232,53.56631551637331]],[[-2.638851529314232,53.56631551637331],[-2.641934359494918,53.56626490196044],[-2.642992828471102,53.56675542273949],[-2.644889907592038,53.565488517712396],[-2.646032320249442,53.565245078537785],[-2.648085992745436,53.567223406146425],[-2.650716061135006,53.568172891994735],[-2.652470683253739,53.56727428760868]],[[-2.691199029552582,53.59591204578603],[-2.688523465301519,53.60358566490499],[-2.687922331319819,53.60407547421088],[-2.6866747810866,53.60394419073005],[-2.686388778648938,53.60345769126758],[-2.685657735342219,53.60339446097305],[-2.685239098142693,53.60302199900631],[-2.684391584489661,53.603043011526104],[-2.682682018514428,53.603692811684695],[-2.68186115800833,53.60349523567765],[-2.681395095623682,53.60374237626175],[-2.678760300770072,53.60381483818159],[-2.67762780709903,53.60444963401005],[-2.676630370940901,53.604454358730266],[-2.676201227423496,53.60474805435594],[-2.67491092762892,53.60458989593638],[-2.674008235064099,53.60484938771654],[-2.673680898119488,53.60460847954927],[-2.672610322679432,53.60476999985633],[-2.671660553369148,53.604542514090745],[-2.66915214705744,53.60487026460457],[-2.667765567596601,53.60416150890444],[-2.666600902800093,53.60410595589209],[-2.665208862824139,53.60323804536784],[-2.664611274134832,53.6033941993446],[-2.66355613708504,53.602995486549965],[-2.662500034998841,53.60321524772147],[-2.65994574768352,53.6031160562579],[-2.657976557461342,53.60341990035788]],[[-2.452697561805764,53.525982141035946],[-2.430948991077031,53.5221491170164]],[[-2.636204600945518,53.545376108628744],[-2.638013705882643,53.54724435110616],[-2.638818736432912,53.54938584866805],[-2.639237587858547,53.56026714094894],[-2.638851529314232,53.56631551637331]],[[-2.662530450709927,53.531408331473195],[-2.660169806253307,53.53038666736221],[-2.659717521155507,53.52982730076016],[-2.660123785030748,53.52936480190056],[-2.658677095301168,53.52811420706214],[-2.658803987878208,53.527054551856324],[-2.658332181073469,53.527176719050715],[-2.65615217643215,53.52542128656845],[-2.653632200637337,53.525678672175125],[-2.65347124080657,53.52472667500184],[-2.651525155819411,53.522762271395116],[-2.650934012839905,53.519522059666556],[-2.651221081671747,53.51669957980791],[-2.650904451372507,53.51385252025025]]],"bbox":[-2.729138979990475,53.44580963450789,-2.413161901585445,53.60806297253214]}
